Workbook

Sheet Dashboard
A1: BACKLOG DASHBOARD
A2: Every figure below is a live formula over the Backlog sheet — change a Status there and this updates.
A4: OVERALL | F4: BY EPIC
A5: Metric | B5: Value | F5: Epic | G5: Name | H5: Phase | I5: Stories | J5: Est. days | K5: Closed | L5: % Done
A6: Total stories | B6: =COUNTA(Backlog!$A$5:$A$219) | F6: E00 | G6: FOUNDATION | H6: 0 | I6: =COUNTIF(Backlog!$B$5:$B$219,$F6) | J6: =SUMIF(Backlog!$B$5:$B$219,$F6,Backlog!$J$5:$J$219) | K6: =COUNTIFS(Backlog!$B$5:$B$219,$F6,Backlog!$E$5:$E$219,"Closed") | L6: =IFERROR($K6/$I6,0)
A7: Total estimated days | B7: =SUM(Backlog!$J$5:$J$219) | F7: E01 | G7: PERSISTENCE & DATA LAYER | H7: 1 | I7: =COUNTIF(Backlog!$B$5:$B$219,$F7) | J7: =SUMIF(Backlog!$B$5:$B$219,$F7,Backlog!$J$5:$J$219) | K7: =COUNTIFS(Backlog!$B$5:$B$219,$F7,Backlog!$E$5:$E$219,"Closed") | L7: =IFERROR($K7/$I7,0)
A8: Closed | B8: =COUNTIF(Backlog!$E$5:$E$219,"Closed") | F8: E02 | G8: BROKER INTEGRATION | H8: 1 | I8: =COUNTIF(Backlog!$B$5:$B$219,$F8) | J8: =SUMIF(Backlog!$B$5:$B$219,$F8,Backlog!$J$5:$J$219) | K8: =COUNTIFS(Backlog!$B$5:$B$219,$F8,Backlog!$E$5:$E$219,"Closed") | L8: =IFERROR($K8/$I8,0)
A9: In flight (Active→QA) | B9: =SUMPRODUCT(COUNTIF(Backlog!$E$5:$E$219,{"Active","Development In-Progress","Development Completed","QA In-Progress","QA-Success"})) | F9: E03 | G9: HISTORICAL DATA | H9: 1 | I9: =COUNTIF(Backlog!$B$5:$B$219,$F9) | J9: =SUMIF(Backlog!$B$5:$B$219,$F9,Backlog!$J$5:$J$219) | K9: =COUNTIFS(Backlog!$B$5:$B$219,$F9,Backlog!$E$5:$E$219,"Closed") | L9: =IFERROR($K9/$I9,0)
A10: Not started (New) | B10: =COUNTIF(Backlog!$E$5:$E$219,"New") | F10: E04 | G10: INDIA HAZARD LISTS | H10: 1 | I10: =COUNTIF(Backlog!$B$5:$B$219,$F10) | J10: =SUMIF(Backlog!$B$5:$B$219,$F10,Backlog!$J$5:$J$219) | K10: =COUNTIFS(Backlog!$B$5:$B$219,$F10,Backlog!$E$5:$E$219,"Closed") | L10: =IFERROR($K10/$I10,0)
A11: Blocked / On Hold | B11: =COUNTIF(Backlog!$E$5:$E$219,"Blocked")+COUNTIF(Backlog!$E$5:$E$219,"On Hold") | F11: E05 | G11: MARKET DATA INGESTION | H11: 1 | I11: =COUNTIF(Backlog!$B$5:$B$219,$F11) | J11: =SUMIF(Backlog!$B$5:$B$219,$F11,Backlog!$J$5:$J$219) | K11: =COUNTIFS(Backlog!$B$5:$B$219,$F11,Backlog!$E$5:$E$219,"Closed") | L11: =IFERROR($K11/$I11,0)
A12: % Complete | B12: =IFERROR(COUNTIF(Backlog!$E$5:$E$219,"Closed")/COUNTA(Backlog!$A$5:$A$219),0) | F12: E06 | G12: TECHNICAL ANALYSIS ENGINE | H12: 2 | I12: =COUNTIF(Backlog!$B$5:$B$219,$F12) | J12: =SUMIF(Backlog!$B$5:$B$219,$F12,Backlog!$J$5:$J$219) | K12: =COUNTIFS(Backlog!$B$5:$B$219,$F12,Backlog!$E$5:$E$219,"Closed") | L12: =IFERROR($K12/$I12,0)
A13: Days closed | B13: =SUMIF(Backlog!$E$5:$E$219,"Closed",Backlog!$J$5:$J$219) | F13: E07 | G13: UNIVERSE & SCORING | H13: 2 | I13: =COUNTIF(Backlog!$B$5:$B$219,$F13) | J13: =SUMIF(Backlog!$B$5:$B$219,$F13,Backlog!$J$5:$J$219) | K13: =COUNTIFS(Backlog!$B$5:$B$219,$F13,Backlog!$E$5:$E$219,"Closed") | L13: =IFERROR($K13/$I13,0)
A14: Days remaining | B14: =SUM(Backlog!$J$5:$J$219)-SUMIF(Backlog!$E$5:$E$219,"Closed",Backlog!$J$5:$J$219) | F14: E08 | G14: NEWS INTELLIGENCE | H14: 3 | I14: =COUNTIF(Backlog!$B$5:$B$219,$F14) | J14: =SUMIF(Backlog!$B$5:$B$219,$F14,Backlog!$J$5:$J$219) | K14: =COUNTIFS(Backlog!$B$5:$B$219,$F14,Backlog!$E$5:$E$219,"Closed") | L14: =IFERROR($K14/$I14,0)
F15: E09 | G15: MACRO CONTEXT | H15: 3 | I15: =COUNTIF(Backlog!$B$5:$B$219,$F15) | J15: =SUMIF(Backlog!$B$5:$B$219,$F15,Backlog!$J$5:$J$219) | K15: =COUNTIFS(Backlog!$B$5:$B$219,$F15,Backlog!$E$5:$E$219,"Closed") | L15: =IFERROR($K15/$I15,0)
A16: BY STATUS | F16: E10 | G16: AI LAYER | H16: 3 | I16: =COUNTIF(Backlog!$B$5:$B$219,$F16) | J16: =SUMIF(Backlog!$B$5:$B$219,$F16,Backlog!$J$5:$J$219) | K16: =COUNTIFS(Backlog!$B$5:$B$219,$F16,Backlog!$E$5:$E$219,"Closed") | L16: =IFERROR($K16/$I16,0)
A17: Status | B17: Stories | C17: % of total | D17: Est. days | F17: E11 | G17: PRE-MARKET ENGINE | H17: 3 | I17: =COUNTIF(Backlog!$B$5:$B$219,$F17) | J17: =SUMIF(Backlog!$B$5:$B$219,$F17,Backlog!$J$5:$J$219) | K17: =COUNTIFS(Backlog!$B$5:$B$219,$F17,Backlog!$E$5:$E$219,"Closed") | L17: =IFERROR($K17/$I17,0)
A18: New | B18: =COUNTIF(Backlog!$E$5:$E$219,$A18) | C18: =IFERROR($B18/COUNTA(Backlog!$A$5:$A$219),0) | D18: =SUMIF(Backlog!$E$5:$E$219,$A18,Backlog!$J$5:$J$219) | F18: E12 | G18: STRATEGY ENGINE | H18: 5 | I18: =COUNTIF(Backlog!$B$5:$B$219,$F18) | J18: =SUMIF(Backlog!$B$5:$B$219,$F18,Backlog!$J$5:$J$219) | K18: =COUNTIFS(Backlog!$B$5:$B$219,$F18,Backlog!$E$5:$E$219,"Closed") | L18: =IFERROR($K18/$I18,0)
A19: Business Review | B19: =COUNTIF(Backlog!$E$5:$E$219,$A19) | C19: =IFERROR($B19/COUNTA(Backlog!$A$5:$A$219),0) | D19: =SUMIF(Backlog!$E$5:$E$219,$A19,Backlog!$J$5:$J$219) | F19: E13 | G19: SIGNAL ENGINE | H19: 4 | I19: =COUNTIF(Backlog!$B$5:$B$219,$F19) | J19: =SUMIF(Backlog!$B$5:$B$219,$F19,Backlog!$J$5:$J$219) | K19: =COUNTIFS(Backlog!$B$5:$B$219,$F19,Backlog!$E$5:$E$219,"Closed") | L19: =IFERROR($K19/$I19,0)
A20: Business Approved | B20: =COUNTIF(Backlog!$E$5:$E$219,$A20) | C20: =IFERROR($B20/COUNTA(Backlog!$A$5:$A$219),0) | D20: =SUMIF(Backlog!$E$5:$E$219,$A20,Backlog!$J$5:$J$219) | F20: E14 | G20: RISK ENGINE | H20: 5 | I20: =COUNTIF(Backlog!$B$5:$B$219,$F20) | J20: =SUMIF(Backlog!$B$5:$B$219,$F20,Backlog!$J$5:$J$219) | K20: =COUNTIFS(Backlog!$B$5:$B$219,$F20,Backlog!$E$5:$E$219,"Closed") | L20: =IFERROR($K20/$I20,0)
A21: Active | B21: =COUNTIF(Backlog!$E$5:$E$219,$A21) | C21: =IFERROR($B21/COUNTA(Backlog!$A$5:$A$219),0) | D21: =SUMIF(Backlog!$E$5:$E$219,$A21,Backlog!$J$5:$J$219) | F21: E15 | G21: EXECUTION & POSITIONS | H21: 5 | I21: =COUNTIF(Backlog!$B$5:$B$219,$F21) | J21: =SUMIF(Backlog!$B$5:$B$219,$F21,Backlog!$J$5:$J$219) | K21: =COUNTIFS(Backlog!$B$5:$B$219,$F21,Backlog!$E$5:$E$219,"Closed") | L21: =IFERROR($K21/$I21,0)
A22: Development In-Progress | B22: =COUNTIF(Backlog!$E$5:$E$219,$A22) | C22: =IFERROR($B22/COUNTA(Backlog!$A$5:$A$219),0) | D22: =SUMIF(Backlog!$E$5:$E$219,$A22,Backlog!$J$5:$J$219) | F22: E16 | G22: AUTONOMY & APPROVAL | H22: 5 | I22: =COUNTIF(Backlog!$B$5:$B$219,$F22) | J22: =SUMIF(Backlog!$B$5:$B$219,$F22,Backlog!$J$5:$J$219) | K22: =COUNTIFS(Backlog!$B$5:$B$219,$F22,Backlog!$E$5:$E$219,"Closed") | L22: =IFERROR($K22/$I22,0)
A23: Development Completed | B23: =COUNTIF(Backlog!$E$5:$E$219,$A23) | C23: =IFERROR($B23/COUNTA(Backlog!$A$5:$A$219),0) | D23: =SUMIF(Backlog!$E$5:$E$219,$A23,Backlog!$J$5:$J$219) | F23: E17 | G23: DASHBOARD UI | H23: 4/6 | I23: =COUNTIF(Backlog!$B$5:$B$219,$F23) | J23: =SUMIF(Backlog!$B$5:$B$219,$F23,Backlog!$J$5:$J$219) | K23: =COUNTIFS(Backlog!$B$5:$B$219,$F23,Backlog!$E$5:$E$219,"Closed") | L23: =IFERROR($K23/$I23,0)
A24: QA In-Progress | B24: =COUNTIF(Backlog!$E$5:$E$219,$A24) | C24: =IFERROR($B24/COUNTA(Backlog!$A$5:$A$219),0) | D24: =SUMIF(Backlog!$E$5:$E$219,$A24,Backlog!$J$5:$J$219) | F24: E18 | G24: ADMIN UI | H24: 6 | I24: =COUNTIF(Backlog!$B$5:$B$219,$F24) | J24: =SUMIF(Backlog!$B$5:$B$219,$F24,Backlog!$J$5:$J$219) | K24: =COUNTIFS(Backlog!$B$5:$B$219,$F24,Backlog!$E$5:$E$219,"Closed") | L24: =IFERROR($K24/$I24,0)
A25: QA-Success | B25: =COUNTIF(Backlog!$E$5:$E$219,$A25) | C25: =IFERROR($B25/COUNTA(Backlog!$A$5:$A$219),0) | D25: =SUMIF(Backlog!$E$5:$E$219,$A25,Backlog!$J$5:$J$219) | F25: E19 | G25: NOTIFICATIONS | H25: 3/4 | I25: =COUNTIF(Backlog!$B$5:$B$219,$F25) | J25: =SUMIF(Backlog!$B$5:$B$219,$F25,Backlog!$J$5:$J$219) | K25: =COUNTIFS(Backlog!$B$5:$B$219,$F25,Backlog!$E$5:$E$219,"Closed") | L25: =IFERROR($K25/$I25,0)
A26: QA-Fail | B26: =COUNTIF(Backlog!$E$5:$E$219,$A26) | C26: =IFERROR($B26/COUNTA(Backlog!$A$5:$A$219),0) | D26: =SUMIF(Backlog!$E$5:$E$219,$A26,Backlog!$J$5:$J$219) | F26: E20 | G26: OBSERVABILITY | H26: 6 | I26: =COUNTIF(Backlog!$B$5:$B$219,$F26) | J26: =SUMIF(Backlog!$B$5:$B$219,$F26,Backlog!$J$5:$J$219) | K26: =COUNTIFS(Backlog!$B$5:$B$219,$F26,Backlog!$E$5:$E$219,"Closed") | L26: =IFERROR($K26/$I26,0)
A27: Closed | B27: =COUNTIF(Backlog!$E$5:$E$219,$A27) | C27: =IFERROR($B27/COUNTA(Backlog!$A$5:$A$219),0) | D27: =SUMIF(Backlog!$E$5:$E$219,$A27,Backlog!$J$5:$J$219) | F27: E21 | G27: COMPLIANCE & TAX | H27: 6 | I27: =COUNTIF(Backlog!$B$5:$B$219,$F27) | J27: =SUMIF(Backlog!$B$5:$B$219,$F27,Backlog!$J$5:$J$219) | K27: =COUNTIFS(Backlog!$B$5:$B$219,$F27,Backlog!$E$5:$E$219,"Closed") | L27: =IFERROR($K27/$I27,0)
A28: Removed | B28: =COUNTIF(Backlog!$E$5:$E$219,$A28) | C28: =IFERROR($B28/COUNTA(Backlog!$A$5:$A$219),0) | D28: =SUMIF(Backlog!$E$5:$E$219,$A28,Backlog!$J$5:$J$219) | F28: E22 | G28: TESTING & VALIDATION | H28: 7 | I28: =COUNTIF(Backlog!$B$5:$B$219,$F28) | J28: =SUMIF(Backlog!$B$5:$B$219,$F28,Backlog!$J$5:$J$219) | K28: =COUNTIFS(Backlog!$B$5:$B$219,$F28,Backlog!$E$5:$E$219,"Closed") | L28: =IFERROR($K28/$I28,0)
A29: Moved to Backlog | B29: =COUNTIF(Backlog!$E$5:$E$219,$A29) | C29: =IFERROR($B29/COUNTA(Backlog!$A$5:$A$219),0) | D29: =SUMIF(Backlog!$E$5:$E$219,$A29,Backlog!$J$5:$J$219) | F29: E23 | G29: DEPLOYMENT & OPS | H29: 7/8 | I29: =COUNTIF(Backlog!$B$5:$B$219,$F29) | J29: =SUMIF(Backlog!$B$5:$B$219,$F29,Backlog!$J$5:$J$219) | K29: =COUNTIFS(Backlog!$B$5:$B$219,$F29,Backlog!$E$5:$E$219,"Closed") | L29: =IFERROR($K29/$I29,0)
A30: Blocked | B30: =COUNTIF(Backlog!$E$5:$E$219,$A30) | C30: =IFERROR($B30/COUNTA(Backlog!$A$5:$A$219),0) | D30: =SUMIF(Backlog!$E$5:$E$219,$A30,Backlog!$J$5:$J$219) | F30: TOTAL | I30: =SUM(I6:I29) | J30: =SUM(J6:J29) | K30: =SUM(K6:K29) | L30: =IFERROR(K30/I30,0)
A31: On Hold | B31: =COUNTIF(Backlog!$E$5:$E$219,$A31) | C31: =IFERROR($B31/COUNTA(Backlog!$A$5:$A$219),0) | D31: =SUMIF(Backlog!$E$5:$E$219,$A31,Backlog!$J$5:$J$219)
A32: TOTAL | B32: =SUM(B18:B31) | C32: =SUM(C18:C31) | D32: =SUM(D18:D31)
A34: BY PRIORITY
A35: Priority | B35: Stories | C35: Est. days | D35: Closed
A36: P0 | B36: =COUNTIF(Backlog!$F$5:$F$219,$A36) | C36: =SUMIF(Backlog!$F$5:$F$219,$A36,Backlog!$J$5:$J$219) | D36: =COUNTIFS(Backlog!$F$5:$F$219,$A36,Backlog!$E$5:$E$219,"Closed")
A37: P1 | B37: =COUNTIF(Backlog!$F$5:$F$219,$A37) | C37: =SUMIF(Backlog!$F$5:$F$219,$A37,Backlog!$J$5:$J$219) | D37: =COUNTIFS(Backlog!$F$5:$F$219,$A37,Backlog!$E$5:$E$219,"Closed")
A38: P2 | B38: =COUNTIF(Backlog!$F$5:$F$219,$A38) | C38: =SUMIF(Backlog!$F$5:$F$219,$A38,Backlog!$J$5:$J$219) | D38: =COUNTIFS(Backlog!$F$5:$F$219,$A38,Backlog!$E$5:$E$219,"Closed")
A39: P3 | B39: =COUNTIF(Backlog!$F$5:$F$219,$A39) | C39: =SUMIF(Backlog!$F$5:$F$219,$A39,Backlog!$J$5:$J$219) | D39: =COUNTIFS(Backlog!$F$5:$F$219,$A39,Backlog!$E$5:$E$219,"Closed")
A41: BY RISK
A42: Risk | B42: Stories | C42: Est. days | D42: Closed
A43: Safety-critical | B43: =COUNTIF(Backlog!$H$5:$H$219,$A43) | C43: =SUMIF(Backlog!$H$5:$H$219,$A43,Backlog!$J$5:$J$219) | D43: =COUNTIFS(Backlog!$H$5:$H$219,$A43,Backlog!$E$5:$E$219,"Closed")
A44: Correctness-critical | B44: =COUNTIF(Backlog!$H$5:$H$219,$A44) | C44: =SUMIF(Backlog!$H$5:$H$219,$A44,Backlog!$J$5:$J$219) | D44: =COUNTIFS(Backlog!$H$5:$H$219,$A44,Backlog!$E$5:$E$219,"Closed")
A45: Low | B45: =COUNTIF(Backlog!$H$5:$H$219,$A45) | C45: =SUMIF(Backlog!$H$5:$H$219,$A45,Backlog!$J$5:$J$219) | D45: =COUNTIFS(Backlog!$H$5:$H$219,$A45,Backlog!$E$5:$E$219,"Closed")
A47: BY TYPE
A48: Type | B48: Stories | C48: Est. days | D48: Closed
A49: FEAT | B49: =COUNTIF(Backlog!$I$5:$I$219,$A49) | C49: =SUMIF(Backlog!$I$5:$I$219,$A49,Backlog!$J$5:$J$219) | D49: =COUNTIFS(Backlog!$I$5:$I$219,$A49,Backlog!$E$5:$E$219,"Closed")
A50: INFRA | B50: =COUNTIF(Backlog!$I$5:$I$219,$A50) | C50: =SUMIF(Backlog!$I$5:$I$219,$A50,Backlog!$J$5:$J$219) | D50: =COUNTIFS(Backlog!$I$5:$I$219,$A50,Backlog!$E$5:$E$219,"Closed")
A51: SEC | B51: =COUNTIF(Backlog!$I$5:$I$219,$A51) | C51: =SUMIF(Backlog!$I$5:$I$219,$A51,Backlog!$J$5:$J$219) | D51: =COUNTIFS(Backlog!$I$5:$I$219,$A51,Backlog!$E$5:$E$219,"Closed")
A52: TEST | B52: =COUNTIF(Backlog!$I$5:$I$219,$A52) | C52: =SUMIF(Backlog!$I$5:$I$219,$A52,Backlog!$J$5:$J$219) | D52: =COUNTIFS(Backlog!$I$5:$I$219,$A52,Backlog!$E$5:$E$219,"Closed")
A53: OPS | B53: =COUNTIF(Backlog!$I$5:$I$219,$A53) | C53: =SUMIF(Backlog!$I$5:$I$219,$A53,Backlog!$J$5:$J$219) | D53: =COUNTIFS(Backlog!$I$5:$I$219,$A53,Backlog!$E$5:$E$219,"Closed")
A54: DOC | B54: =COUNTIF(Backlog!$I$5:$I$219,$A54) | C54: =SUMIF(Backlog!$I$5:$I$219,$A54,Backlog!$J$5:$J$219) | D54: =COUNTIFS(Backlog!$I$5:$I$219,$A54,Backlog!$E$5:$E$219,"Closed")
A58: CHARTS
A59: Every figure below is a live formula over the Backlog sheet — the charts redraw themselves when a story's Status or Est. Days changes. Nothing here is hand-typed.
A60: Status | B60: Stories
A61: New | B61: =COUNTIF(Backlog!$E$5:$E$219,$A$61)
A62: Business Review | B62: =COUNTIF(Backlog!$E$5:$E$219,$A$62)
A63: Business Approved | B63: =COUNTIF(Backlog!$E$5:$E$219,$A$63)
A64: Active | B64: =COUNTIF(Backlog!$E$5:$E$219,$A$64)
A65: Development In-Progress | B65: =COUNTIF(Backlog!$E$5:$E$219,$A$65)
A66: Development Completed | B66: =COUNTIF(Backlog!$E$5:$E$219,$A$66)
A67: QA In-Progress | B67: =COUNTIF(Backlog!$E$5:$E$219,$A$67)
A68: QA-Success | B68: =COUNTIF(Backlog!$E$5:$E$219,$A$68)
A69: QA-Fail | B69: =COUNTIF(Backlog!$E$5:$E$219,$A$69)
A70: Closed | B70: =COUNTIF(Backlog!$E$5:$E$219,$A$70)
A71: Blocked | B71: =COUNTIF(Backlog!$E$5:$E$219,$A$71)
A72: On Hold | B72: =COUNTIF(Backlog!$E$5:$E$219,$A$72)
A73: Moved to Backlog | B73: =COUNTIF(Backlog!$E$5:$E$219,$A$73)
A75: Effort by phase (days)
A76: Phase | B76: Closed | C76: Remaining
A77: 0 | B77: =SUMIFS(Backlog!$J$5:$J$219,Backlog!$G$5:$G$219,$A$77,Backlog!$E$5:$E$219,"Closed") | C77: =SUMIF(Backlog!$G$5:$G$219,$A$77,Backlog!$J$5:$J$219)-$B$77
A78: 1 | B78: =SUMIFS(Backlog!$J$5:$J$219,Backlog!$G$5:$G$219,$A$78,Backlog!$E$5:$E$219,"Closed") | C78: =SUMIF(Backlog!$G$5:$G$219,$A$78,Backlog!$J$5:$J$219)-$B$78
A79: 2 | B79: =SUMIFS(Backlog!$J$5:$J$219,Backlog!$G$5:$G$219,$A$79,Backlog!$E$5:$E$219,"Closed") | C79: =SUMIF(Backlog!$G$5:$G$219,$A$79,Backlog!$J$5:$J$219)-$B$79
A80: 3 | B80: =SUMIFS(Backlog!$J$5:$J$219,Backlog!$G$5:$G$219,$A$80,Backlog!$E$5:$E$219,"Closed") | C80: =SUMIF(Backlog!$G$5:$G$219,$A$80,Backlog!$J$5:$J$219)-$B$80
A81: 4 | B81: =SUMIFS(Backlog!$J$5:$J$219,Backlog!$G$5:$G$219,$A$81,Backlog!$E$5:$E$219,"Closed") | C81: =SUMIF(Backlog!$G$5:$G$219,$A$81,Backlog!$J$5:$J$219)-$B$81
A82: 5 | B82: =SUMIFS(Backlog!$J$5:$J$219,Backlog!$G$5:$G$219,$A$82,Backlog!$E$5:$E$219,"Closed") | C82: =SUMIF(Backlog!$G$5:$G$219,$A$82,Backlog!$J$5:$J$219)-$B$82
A83: 6 | B83: =SUMIFS(Backlog!$J$5:$J$219,Backlog!$G$5:$G$219,$A$83,Backlog!$E$5:$E$219,"Closed") | C83: =SUMIF(Backlog!$G$5:$G$219,$A$83,Backlog!$J$5:$J$219)-$B$83
A84: 7 | B84: =SUMIFS(Backlog!$J$5:$J$219,Backlog!$G$5:$G$219,$A$84,Backlog!$E$5:$E$219,"Closed") | C84: =SUMIF(Backlog!$G$5:$G$219,$A$84,Backlog!$J$5:$J$219)-$B$84
A85: 8 | B85: =SUMIFS(Backlog!$J$5:$J$219,Backlog!$G$5:$G$219,$A$85,Backlog!$E$5:$E$219,"Closed") | C85: =SUMIF(Backlog!$G$5:$G$219,$A$85,Backlog!$J$5:$J$219)-$B$85
A87: Epic completion
A88: Epic | B88: % complete
A89: =$F$6 | B89: =IFERROR(SUMIFS(Backlog!$J$5:$J$219,Backlog!$B$5:$B$219,$A$89,Backlog!$E$5:$E$219,"Closed")/SUMIF(Backlog!$B$5:$B$219,$A$89,Backlog!$J$5:$J$219),0)
A90: =$F$7 | B90: =IFERROR(SUMIFS(Backlog!$J$5:$J$219,Backlog!$B$5:$B$219,$A$90,Backlog!$E$5:$E$219,"Closed")/SUMIF(Backlog!$B$5:$B$219,$A$90,Backlog!$J$5:$J$219),0)
A91: =$F$8 | B91: =IFERROR(SUMIFS(Backlog!$J$5:$J$219,Backlog!$B$5:$B$219,$A$91,Backlog!$E$5:$E$219,"Closed")/SUMIF(Backlog!$B$5:$B$219,$A$91,Backlog!$J$5:$J$219),0)
A92: =$F$9 | B92: =IFERROR(SUMIFS(Backlog!$J$5:$J$219,Backlog!$B$5:$B$219,$A$92,Backlog!$E$5:$E$219,"Closed")/SUMIF(Backlog!$B$5:$B$219,$A$92,Backlog!$J$5:$J$219),0)
A93: =$F$10 | B93: =IFERROR(SUMIFS(Backlog!$J$5:$J$219,Backlog!$B$5:$B$219,$A$93,Backlog!$E$5:$E$219,"Closed")/SUMIF(Backlog!$B$5:$B$219,$A$93,Backlog!$J$5:$J$219),0)
A94: =$F$11 | B94: =IFERROR(SUMIFS(Backlog!$J$5:$J$219,Backlog!$B$5:$B$219,$A$94,Backlog!$E$5:$E$219,"Closed")/SUMIF(Backlog!$B$5:$B$219,$A$94,Backlog!$J$5:$J$219),0)
A95: =$F$12 | B95: =IFERROR(SUMIFS(Backlog!$J$5:$J$219,Backlog!$B$5:$B$219,$A$95,Backlog!$E$5:$E$219,"Closed")/SUMIF(Backlog!$B$5:$B$219,$A$95,Backlog!$J$5:$J$219),0)
A96: =$F$13 | B96: =IFERROR(SUMIFS(Backlog!$J$5:$J$219,Backlog!$B$5:$B$219,$A$96,Backlog!$E$5:$E$219,"Closed")/SUMIF(Backlog!$B$5:$B$219,$A$96,Backlog!$J$5:$J$219),0)
A97: =$F$14 | B97: =IFERROR(SUMIFS(Backlog!$J$5:$J$219,Backlog!$B$5:$B$219,$A$97,Backlog!$E$5:$E$219,"Closed")/SUMIF(Backlog!$B$5:$B$219,$A$97,Backlog!$J$5:$J$219),0)
A98: =$F$15 | B98: =IFERROR(SUMIFS(Backlog!$J$5:$J$219,Backlog!$B$5:$B$219,$A$98,Backlog!$E$5:$E$219,"Closed")/SUMIF(Backlog!$B$5:$B$219,$A$98,Backlog!$J$5:$J$219),0)
A99: =$F$16 | B99: =IFERROR(SUMIFS(Backlog!$J$5:$J$219,Backlog!$B$5:$B$219,$A$99,Backlog!$E$5:$E$219,"Closed")/SUMIF(Backlog!$B$5:$B$219,$A$99,Backlog!$J$5:$J$219),0)
A100: =$F$17 | B100: =IFERROR(SUMIFS(Backlog!$J$5:$J$219,Backlog!$B$5:$B$219,$A$100,Backlog!$E$5:$E$219,"Closed")/SUMIF(Backlog!$B$5:$B$219,$A$100,Backlog!$J$5:$J$219),0)
A101: =$F$18 | B101: =IFERROR(SUMIFS(Backlog!$J$5:$J$219,Backlog!$B$5:$B$219,$A$101,Backlog!$E$5:$E$219,"Closed")/SUMIF(Backlog!$B$5:$B$219,$A$101,Backlog!$J$5:$J$219),0)
A102: =$F$19 | B102: =IFERROR(SUMIFS(Backlog!$J$5:$J$219,Backlog!$B$5:$B$219,$A$102,Backlog!$E$5:$E$219,"Closed")/SUMIF(Backlog!$B$5:$B$219,$A$102,Backlog!$J$5:$J$219),0)
A103: =$F$20 | B103: =IFERROR(SUMIFS(Backlog!$J$5:$J$219,Backlog!$B$5:$B$219,$A$103,Backlog!$E$5:$E$219,"Closed")/SUMIF(Backlog!$B$5:$B$219,$A$103,Backlog!$J$5:$J$219),0)
A104: =$F$21 | B104: =IFERROR(SUMIFS(Backlog!$J$5:$J$219,Backlog!$B$5:$B$219,$A$104,Backlog!$E$5:$E$219,"Closed")/SUMIF(Backlog!$B$5:$B$219,$A$104,Backlog!$J$5:$J$219),0)
A105: =$F$22 | B105: =IFERROR(SUMIFS(Backlog!$J$5:$J$219,Backlog!$B$5:$B$219,$A$105,Backlog!$E$5:$E$219,"Closed")/SUMIF(Backlog!$B$5:$B$219,$A$105,Backlog!$J$5:$J$219),0)
A106: =$F$23 | B106: =IFERROR(SUMIFS(Backlog!$J$5:$J$219,Backlog!$B$5:$B$219,$A$106,Backlog!$E$5:$E$219,"Closed")/SUMIF(Backlog!$B$5:$B$219,$A$106,Backlog!$J$5:$J$219),0)
A107: =$F$24 | B107: =IFERROR(SUMIFS(Backlog!$J$5:$J$219,Backlog!$B$5:$B$219,$A$107,Backlog!$E$5:$E$219,"Closed")/SUMIF(Backlog!$B$5:$B$219,$A$107,Backlog!$J$5:$J$219),0)
A108: =$F$25 | B108: =IFERROR(SUMIFS(Backlog!$J$5:$J$219,Backlog!$B$5:$B$219,$A$108,Backlog!$E$5:$E$219,"Closed")/SUMIF(Backlog!$B$5:$B$219,$A$108,Backlog!$J$5:$J$219),0)
A109: =$F$26 | B109: =IFERROR(SUMIFS(Backlog!$J$5:$J$219,Backlog!$B$5:$B$219,$A$109,Backlog!$E$5:$E$219,"Closed")/SUMIF(Backlog!$B$5:$B$219,$A$109,Backlog!$J$5:$J$219),0)
...

Sheet Backlog
A1: DEVELOPMENT BACKLOG — User Stories & Tasks
A2: Source: BACKLOG.md · 189 stories across 24 epics · Set Status from the dropdown in column E. Yellow-tinted columns (M–Q, W) are yours to fill in. Tasks/Acceptance are wrapped — widen a row or click a cell to read the full text.
A4: Story ID | B4: Epic | C4: Epic Name | D4: Story Title | E4: Status | F4: Priority | G4: Phase | H4: Risk | I4: Type | J4: Est. Days | K4: Dependencies | L4: Blocked By | M4: Owner | N4: Sprint | O4: Start Date | P4: Target Date | Q4: % Complete | R4: Task Count | S4: User Story | T4: Tasks | U4: Acceptance Criteria | V4: Notes | W4: Comments | X4: Build Concerns
A5: E00-S01 | B5: E00 | C5: FOUNDATION | D5: Project scaffold, packaging, tooling | E5: Closed | F5: P0 | G5: 0 | H5: Low | I5: INFRA | R5: 0
A6: E00-S02 | B6: E00 | C6: FOUNDATION | D6: Domain models with Decimal money and tz-aware UTC | E6: Closed | F6: P0 | G6: 0 | H6: Correctness-critical | I6: INFRA | R6: 0
A7: E00-S03 | B7: E00 | C7: FOUNDATION | D7: Config validation with hard bounds in code | E7: Closed | F7: P0 | G7: 0 | H7: Safety-critical | I7: INFRA | R7: 0
A8: E00-S04 | B8: E00 | C8: FOUNDATION | D8: Secrets handling that cannot render | E8: Closed | F8: P0 | G8: 0 | H8: Safety-critical | I8: INFRA | R8: 0
A9: E00-S05 | B9: E00 | C9: FOUNDATION | D9: Structured logging with mandatory redaction | E9: Closed | F9: P0 | G9: 0 | H9: Safety-critical | I9: INFRA | R9: 0
A10: E00-S06 | B10: E00 | C10: FOUNDATION | D10: NSE calendar with per-stock square-off | E10: Closed | F10: P0 | G10: 0 | H10: Safety-critical | I10: INFRA | R10: 0
A11: E00-S07 | B11: E00 | C11: FOUNDATION | D11: Broker protocol, read-only vs trading split | E11: Closed | F11: P0 | G11: 0 | H11: Safety-critical | I11: INFRA | R11: 0
A12: E00-S08 | B12: E00 | C12: FOUNDATION | D12: Strategy DSL with vetted primitive registry | E12: Closed | F12: P0 | G12: 0 | H12: Safety-critical | I12: INFRA | R12: 0
A13: E00-S09 | B13: E00 | C13: FOUNDATION | D13: Docker topology with network segmentation | E13: Closed | F13: P0 | G13: 0 | H13: Correctness-critical | I13: INFRA | R13: 0 | V13: written, not run
A14: E00-S10 | B14: E00 | C14: FOUNDATION | D14: Pre-flight doctor script | E14: Closed | F14: P0 | G14: 0 | H14: Low | I14: INFRA | R14: 0
A15: E01-S01 | B15: E01 | C15: PERSISTENCE & DATA LAYER | D15: Database schema and migrations | E15: Closed | F15: P0 | G15: 1 | H15: Correctness-critical | I15: INFRA | J15: 2 | K15: none | N15: 1 | Q15: 100 | R15: 9 | S15: As a developer, I want the full database schema defined as versioned migrations, so that schema changes are reviewable and reversible rather than applied by hand. | T15: 1. Set up Alembic with async SQLAlchemy 2.0 2. SQLAlchemy models mirroring LOW_LEVEL_ARCHITECTURE §4.2 3. Migration: instruments, instrument_daily_status 4. Migration: ohlcv as a TimescaleDB hypertable 5. Migration: orders, positions, decision_log, trade_journal 6. Migration: daily_plan, plan_candidate 7. Migration: strategy, strategy_validation, strategy_trial, strategy_performance, shadow_signal 8. Compression policy on ohlcv (>90 days) 9. `make migrate` target | U15: • `alembic upgrade head` then `downgrade base` runs clean on an empty DB • Hypertables confirmed via `SELECT * FROM timescaledb_information.hypertables` • `decision_log` and `strategy_trial` roles have INSERT but not UPDATE/DELETE | V15: CLOSED 7 Aug 2026. Schema, migrations and role grants complete; 38 integration tests assert every business rule against a real TimescaleDB. DELIVERED: 15 tables in common/db/models.py; two migrations (core schema autogenerated, hypertables/view/grants hand-written); upgrade head -> downgrade base -> upgrade head verified clean. DECISIONS TAKEN: - TimescaleDB DDL is VERSION-ADAPTIVE. The migration detects the installed version and emits columnstore DDL at >=2.18 or legacy compression below it. Verified on BOTH 2.17.2 and 2.29.1, so the pin decision no longer blocks anything and can move either way later. - Role created NOLOGIN/password-less; operator grants LOGIN out of band. The spec's CREATE ROLE ... PASSWORD would have committed a credential. - v_eligible_today anchored to Asia/Kolkata, not CURRENT_DATE. FOUR BUGS FOUND BY EXECUTION (all fixed, all now covered by tests): 1. SQLAlchemy Enum(native_enum=False) defaults create_constraint=FALSE since 1.4 — the enum columns had NO validation at all. An invalid 'side' went straight in. Only the column length was accidentally guarding them. 2. decision_log.id was NOT NULL with no sequence: SQLAlchemy attaches an implicit sequence only to a PRIMARY KEY, and this is not one. EVERY insert failed. Fixed with an explicit Identity(). 3. order_fills generated-column DDL in the spec was invalid PostgreSQL. 4. Enum columns sized to an exact fit meant truncation errors fired before CHECK constraints, producing an error naming neither column nor expected value. NOT a bug but worth knowing: autogenerate cannot render ORM attributes in postgresql_where; partial index predicates use sa.text(). | W15: Open questions to settle inside this story (§17): Q1 RESOLVED — pin is 2.17.2-pg16; upgrade decision is yours, recommended. Q2 Retention of 1m bars — recommend keep forever; ~19M rows either way, storage is not the constraint, backtest depth is. Q3 DB roles — recommend one app role now, split per-service at Phase 7. Q4 Audit buffer location — recommend host mount (survives image rebuild). Watch: TimescaleDB requires the partitioning column in every unique index; downgrade must drop policies before hypertables; test 'downgrade base' on every migration.
A16: E01-S02 | B16: E01 | C16: PERSISTENCE & DATA LAYER | D16: Repository layer | E16: Closed | F16: P0 | G16: 1 | H16: Low | I16: INFRA | J16: 2 | K16: E01-S01 | N16: 1 | Q16: 100 | R16: 5 | S16: As a developer, I want data access behind repository interfaces, so that services never write raw SQL and can be tested against fakes. | T16: 1. `Repository` protocol per aggregate (instruments, bars, orders, positions, plan, strategy) 2. Async session management with proper transaction boundaries 3. Bulk insert path for OHLCV (batched, not row-by-row) 4. Connection pooling configured 5. In-memory fakes for unit tests | U16: • No service module imports `sqlalchemy` directly • Bulk insert of 100k bars completes in < 10s | V16: CLOSED 7 Aug 2026. Repository layer complete; 25 integration tests, both acceptance criteria measured rather than asserted. DELIVERED: common/db/engine.py (async engine, session factory, unit_of_work / read_only boundaries) and common/db/repositories.py (Instrument, Bar, DailyStatus, Order, Position, DecisionLog-read repositories plus Protocols). THE ARCHITECTURE THIS STORY OWNS — the symbol <-> symbol_id impedance mismatch (spec §2.3 E). Domain models address instruments by ticker; every table uses an integer FK. InstrumentRepository holds a bidirectional cache and is the ONLY component permitted to translate. Proven: 50 lookups issue 0 queries. THREE REAL BUGS FOUND BY EXECUTION: 1. POSTGRESQL CAPS BOUND PARAMETERS AT 65535. A bar has up to 12 columns, so the spec's "one TX per batch of ~10k" sends ~120,000 parameters and fails outright with "number of parameters must be between 0 and 65535". This would have surfaced during the 24-MILLION-row historical backfill, not in any unit test. bulk_upsert now chunks INTERNALLY against the parameter limit, sized off the WIDEST row (sizing off the first row under-counts when callers omit optional columns), so no caller can hit it. 2. Chunked multi-row INSERT was correct but SLOW — 100k bars in 23.8s against a 10s budget. Implemented the spec's COPY path (task 3): COPY into a temp table, then one set-based INSERT ... SELECT ... ON CONFLICT DO UPDATE. Now inside budget. COPY cannot express ON CONFLICT itself, which is why the temp table exists. 3. The COPY path needed CREATE TEMP TABLE IF NOT EXISTS + TRUNCATE, not a bare CREATE. ON COMMIT DROP only fires at COMMIT, so the SECOND chunk of a backfill inside one transaction failed with "relation _bar_load already exists". Also: DISTINCT ON (symbol_id, timeframe, ts) ORDER BY ... ctid DESC in the COPY upsert. ON CONFLICT raises "cannot affect row a second time" when the SOURCE holds duplicate keys, which a batch spanning a reconnect legitimately does. Last occurrence wins, matching the INSERT path. Also: the Windows ProactorEventLoop defect RESURFACED in pytest-asyncio. configure_event_loop_policy() must run BEFORE the loop is created; calling it inside create_engine was too late because pytest-asyncio had already built one. Now called at tests/conftest.py import time. Lesson recorded: every async entry point owns that responsibility separately. DESIGN DECISIONS AND WHY: - Repositories return plain dicts, never ORM instances. An ORM object carries session affinity and lazy loaders; once its session closes, touching an unloaded attribute raises MissingGreenlet deep inside business logic. A dict cannot. - warm_up_batch is ONE query with a window function. A per-symbol loop is correct and passes every other test, then misses the 45-minute BP-2 deadline with 450 round trips. The test asserts the QUERY COUNT is constant regardless of symbol count, so that refactor fails here rather than at 08:45 on a trading morning. - expire_on_commit=False: the default makes every attribute a fresh SELECT after commit, and in async code that lazy load raises MissingGreenlet rather than merely being slow. - Server-side statement_timeout, not a client-side cancel. A client-side timeout abandons the query while the server keeps executing it. - read_only() rolls back rather than commits — releases the snapshot immediately, so a long idle-in-transaction session cannot hold back vacuum across the database. - ON CONFLICT DO UPDATE, not DO NOTHING: a late trade report legitimately revises volume and vwap, and a corporate action re-adjusts prices. DO NOTHING would silently pin stale data. - UnknownSymbolError raises rather than returning None. Silently skipping an unknown symbol loses market data with NO error; the gap surfaces days later as an indicator that never warms up. SECURITY: the COPY path builds SQL identifiers by f-string because PostgreSQL cannot parameterise identifiers. Every interpolated value comes from a fixed tuple in the function and is unreachable from market data, news or any request. Justified in place with a noqa so it does not need re-deriving at review time; all VALUES still go through COPY's binary protocol or bound parameters.
A17: E01-S03 | B17: E01 | C17: PERSISTENCE & DATA LAYER | D17: Redis client and keyspace helpers | E17: Closed | F17: P0 | G17: 1 | H17: Correctness-critical | I17: INFRA | J17: 1.5 | K17: none | N17: 1 | Q17: 100 | R17: 6 | S17: As a developer, I want typed helpers for the Redis keyspace, so that key naming cannot drift between services. | T17: 1. Async Redis client with connection pooling and retry 2. Key builders for every pattern in LOW_LEVEL_ARCHITECTURE §4.3 3. Typed get/set for state hashes (Pydantic in, Pydantic out) 4. Distributed lock helper with mandatory TTL 5. Token bucket rate limiter 6. Sorted-set timer helper | U17: • Every key in the design doc has a builder function • A lock without a TTL is impossible to create (TTL is a required arg) | V17: CLOSED 7 Aug 2026. Redis layer complete; 35 integration tests, all probing real behaviour against a real Redis. DELIVERED: common/redis/ — keys.py (23 key builders, no literal permitted elsewhere), client.py (pool, retry, health), locks.py (mandatory TTL), primitives.py (token bucket + timer ZSET, both Lua), state.py (typed Pydantic accessors). THE STORY'S REAL CONTENT — ttl_ms is a REQUIRED positional argument with no default. A lock without a TTL survives the death of the process holding it and deadlocks slot allocation for the rest of the session, silently. Also bounded above (MAX_TTL_MS 300s) to catch seconds-passed-as-milliseconds, which is the realistic mistake. DESIGN DECISIONS AND WHY: - Release/extend are compare-and-delete in Lua. The naive get-then-delete is a race: the lock can expire between check and delete, be re-acquired by another process, and you then delete THEIR lock. - Token bucket and pop-due are Lua for the same reason. A Python-side get/compute/set lets two callers see the same token count and both proceed — for the order limiter that means breaching the broker cap and, above 10/sec, the SEBI threshold. Proven by a 25-way concurrent test that must yield exactly capacity. - decode_responses=True is load-bearing, not cosmetic. Without it every read is bytes and b"1" != "1", so a kill-switch check silently reads as "not set" and trading continues. - Invalid stored state is treated as ABSENT, not raised. Half-valid trading state is worse than none because the system keeps acting on it; absent routes into the existing fail-closed path (no indicators -> no signal). Logged loudly. - is_kill_switch_active FAILS CLOSED — an unreachable Redis returns True (halted). A false halt costs a trade; a false all-clear costs an uncontrolled position. Tested against a dead endpoint. - assert_noeviction() refuses to start if Redis is not noeviction, because under any eviction policy Redis silently discards positions or the kill switch with no error at the point of loss. ISSUES FOUND AND FIXED DURING THE BUILD: 1. bandit S105 false-positived on _TOKEN_BUCKET_LUA (matches "token" in the identifier). A noqa CANNOT go on that line — it ends by opening a triple-quoted string, so the comment becomes Lua source, and # is not a comment in Lua, which silently corrupts the script. Renamed the constant instead. 2. Package named common/redis shadows the library by name; verified safe because Python 3 uses absolute imports. Documented in __init__. NOT DONE HERE: stream helpers live in E01-S04; keys.py already provides their key builders.
A18: E01-S04 | B18: E01 | C18: PERSISTENCE & DATA LAYER | D18: Event stream abstraction | E18: Closed | F18: P0 | G18: 1 | H18: Correctness-critical | I18: INFRA | J18: 1.5 | K18: E01-S03 | N18: 1 | Q18: 100 | R18: 6 | S18: As a developer, I want a typed wrapper over Redis Streams with consumer groups, so that no event is lost when a consumer restarts. | T18: 1. `EventStream` publish/subscribe with Pydantic envelopes 2. Consumer group creation and management 3. Explicit acknowledgement 4. Pending-entry recovery on restart 5. Dead-letter handling after N failures 6. `schema_version` on every envelope | U18: • Kill a consumer mid-stream; on restart it processes the unacked backlog • Messages published while a consumer is down are delivered on return | V18: CLOSED 7 Aug 2026. Event stream layer complete; 27 integration tests including the epic's headline acceptance criterion. DELIVERED: common/events/ — envelope.py (versioned, immutable, correlation-carrying) and stream.py (publish, consumer groups, backlog recovery, reclaim, dead-letter). THE STORY'S REAL CONTENT — maxlen is a REQUIRED keyword argument on publish(), with no default. Redis runs maxmemory 2gb + noeviction. That policy is right (trading state must never be silently evicted) but it means an untrimmed stream does NOT drop old entries — it fills memory and Redis then REFUSES ALL WRITES, system-wide, mid-session. stream:ticks alone is ~10 MB/day. A stream publishable without a bound should not be constructible, and now is not. ACCEPTANCE CRITERION PROVEN: test_crash_mid_stream_loses_nothing — publish 100, consume+ack 50, strand 10 unacked (the crash), restart, assert all 100 processed and pending == 0. This catches the single easiest mistake in the component: on restart a consumer MUST read its own pending backlog at id '0' first. A '>' read returns only NEW messages, so every entry in flight at the moment of a crash is invisible and stranded forever. Backlog is also drained BEFORE new messages, since taking new work ahead of older unacked work reorders the stream from the consumer's view. DESIGN DECISIONS AND WHY: - At-least-once delivery, consumers idempotent. Correct rather than a limitation: a bar processed twice yields the same indicator state; a duplicate signal is caught by lock:symbol and uq_open_symbol; a duplicate audit event by message_id. Exactly-once would need distributed transactions across Redis and Postgres for no practical gain. - Approximate trimming (MAXLEN ~). The property needed is "bounded", not "exactly N"; exact trimming is materially more expensive. The test asserts boundedness, not equality, so it does not encode a Redis implementation detail. - Dead-letter writes to the DLQ BEFORE acking the original. If the process dies between the two the entry stays pending and is retried — recoverable. Acking first would lose it outright. - A malformed entry is logged and SKIPPED, never raised out of the read loop. One poisoned message must not stop the stream. Envelope.from_fields raises ValueError specifically so consumers can catch a narrow type to dead-letter. - schema_version present from message one — retrofitting it onto streams that already hold unversioned entries means writing a shim that guesses. - Consumer names carry a uuid suffix. Two processes sharing a name share a pending list, so one can acknowledge the other's in-flight work. - Payload is nested JSON in ONE stream field, not spread across fields. Redis stream fields are a flat string map; flattening would lose type information exactly where Decimal matters. ISSUE FOUND AND FIXED: redis-py types the xadd field map as an invariant dict of bytes|str|int|float; dict[str, str] is a valid subset but mypy will not narrow it. Cast with the reason recorded in place rather than loosening the function signature.
A19: E01-S05 | B19: E01 | C19: PERSISTENCE & DATA LAYER | D19: Audit log writer with hash chaining | E19: Closed | F19: P0 | G19: 1 | H19: Safety-critical | I19: SEC | J19: 1 | K19: E01-S01 | N19: 1 | Q19: 100 | R19: 5 | S19: As an operator, I want every decision written to an append-only hash-chained log, so that tampering is detectable and I can substantiate any trade. | T19: 1. `AuditWriter` — append-only, never updates 2. Hash chain: each row includes the previous row's hash 3. `correlation_id` on every entry 4. Chain verification utility 5. Buffer to disk if the DB is unavailable, replay on recovery | U19: • Modifying a historical row is detected by the verifier • DB outage does not lose audit entries | V19: CLOSED 7 Aug 2026. SAFETY-CRITICAL (red) — the strict DoD was met in full and NOT relaxed by the reprioritisation. 30 tests: property-based over generated sequences, explicit tamper tests, explicit outage tests, and a concurrency test. DELIVERED: common/audit.py — canonical_json, compute_row_hash, AuditEntry, AuditWriter (with disk buffer), verify_chain. THREE PROPERTIES, EACH ENFORCED STRUCTURALLY: 1. Cannot be modified or deleted — the app role has INSERT but no UPDATE/DELETE (E01-S01 grants). Append-only by convention is a promise; by a missing grant it is a guarantee. 2. Tampering is DETECTABLE even by someone who bypasses the grants. Each row hashes its predecessor's hash, so altering any historical row invalidates every hash after it. Tested: a modified payload, a flipped REJECT->ALLOW, a deleted row, and — the important one — a LOCALLY CONSISTENT FORGERY where the attacker recomputes that row's own hash. It still breaks, at the NEXT row. Hiding a change requires recomputing the entire remaining chain. 3. Survives the DB being down. Entries buffer to disk (fsync per line) and replay in order on recovery; the chain is computed at replay time because a buffered entry's position is not knowable while the DB is down. DESIGN DECISIONS AND WHY: - AuditWriter takes a session FACTORY, never a session. An audit entry written inside a business transaction VANISHES when that transaction rolls back — and a failed attempt is often exactly what you need to investigate. Making it a factory means sharing a transaction is impossible, not merely discouraged. - pg_advisory_xact_lock, taken BEFORE reading the chain head. Read-then-lock lets two writers observe the same prev_hash and fork the chain — and a forked chain fails verification with no tampering having occurred. Transaction-scoped so a crashed writer cannot leak the lock. Proven by a 20-write concurrent test asserting one valid chain with contiguous seq. - write() NEVER raises on a DB failure. An audit write that killed the caller would mean a database blip stops trading AND loses the record of why. - canonical_json with sort_keys: Python dicts are insertion-ordered, so the same logical payload built by two code paths would hash differently and fail verification for no reason. - Timestamps normalised to UTC before hashing, so a row hashed in one timezone verifies in another. Naive timestamps are refused outright. - GLOBAL chain, not per-correlation_id. The per-correlation alternative is simpler and lock-free but CANNOT detect deletion of an entire trade's worth of entries — precisely the tampering worth defending against. Tested. - A failed replay KEEPS the buffer file for retry. Deleting first and failing after would lose entries permanently; retrying at worst duplicates, which is recoverable. ISSUE FOUND AND FIXED: create_engine_from_url had no connect timeout, so the outage tests pointed at a dead endpoint HUNG the suite on the OS TCP timeout (minutes). Added connect_timeout, defaulting to 10s. This is a production concern too, not just a test one: without it "the database is down" presents as "the process appears to hang", which is a far worse failure to diagnose at 09:15. SECURITY: verify_chain originally interpolated its WHERE clause and needed an S608 suppression that kept drifting as the formatter reflowed the string. Rewritten as a four-entry lookup table of complete literal queries — no interpolation at all, so there is no injection surface to justify rather than a justified one. Better answer than a noqa. | X19: The hash chain cannot detect TRUNCATION. Deleting the last N rows leaves a perfectly valid chain — verification passes. The append-only GRANT is the real control there and it is tested, but if you ever need tamper-evidence against someone with DB owner rights, that needs an external anchor (periodically publishing the tip hash somewhere the DB cannot reach). Decide whether that is in scope before relying on the chain for a compliance claim.
A20: E01-S06 | B20: E01 | C20: PERSISTENCE & DATA LAYER | D20: Data retention and archival | E20: Closed | F20: P2 | G20: 6 | H20: Low | I20: OPS | J20: 0.5 | K20: E01-S01 | N20: 16 | Q20: 100 | R20: 3 | S20: As an operator, I want old tick data archived to Parquet, so that the database stays small without losing replay capability. | T20: 1. Nightly job: ticks older than 24h → Parquet 2. Compression policy verification 3. Restore-from-archive utility | V20: CLOSED 7 Aug 2026. Retention, archival and restore complete; 16 integration tests. This was P2/Phase 6 and originally scheduled for Sprint 16 — built now because the direction is to complete every E01 item and it has no blocker. DELIVERED: common/db/retention.py — archive_bars, read_archive, restore_bars, purge_archived_bars, compression_status. THE SAFETY PROPERTY THIS STORY IS REALLY ABOUT — market data CANNOT BE RE-DERIVED. A gap is permanent and silently corrupts every future backtest over that window. So: - archive_bars WRITES AND READS BACK, comparing row counts, before returning. A write that reports success having produced a truncated file is exactly the failure an archive must not have, and it is only detectable by reading. - Nothing in archive_bars deletes. purge_archived_bars is a SEPARATE call that re-reads the archive and refuses unless it holds at least as many rows as the database does for that range. Both refusals are tested, each paired with a control proving the refusal is targeted rather than blanket. - An EMPTY range is refused outright. An empty archive would later look like a verified archive of nothing and could authorise a purge of data it never held. - The full cycle is tested: archive -> purge -> restore -> prices still exact. An archive nobody has restored from is a hypothesis, not a backup. DESIGN DECISIONS AND WHY: - Decimals are archived as STRINGS, not floats. A float round trip loses exactness and would silently corrupt every archived price — the one thing this file exists to preserve faithfully. Asserted directly. - Parquet over CSV: columnar, ~10x compression on this shape, preserves types, and readable by pandas/DuckDB/Polars with no loader. CSV would turn every Decimal into a string and every timestamp into an ambiguous one. - restore uses ON CONFLICT DO NOTHING, not DO UPDATE. The archive is older by definition, so the live copy is authoritative; a restore that overwrote would roll back corrections that arrived after the archive was taken. Tested. - compression_status treats ZERO compressed chunks as HEALTHY on a young database — nothing is 90 days old yet. What matters is that the policy is scheduled and its last run did not fail. A policy that silently stops converting produces no error at all; the first symptom is the disk filling weeks later. DEPENDENCY DECISION (procedure §8.2 — a decision, not a blocker): pyarrow was not installed or declared. Added as a main dependency at >=18.0 (installed 25.0.0). It is large (~100 MB) but is the standard implementation and the archive job runs in the same deployment as everything else. Also added to the mypy ignore_missing_imports overrides, since it ships no stubs.
A21: E01-S07 | B21: E01 | C21: PERSISTENCE & DATA LAYER | D21: Datastore scaffolding and Alembic bootstrap | E21: Closed | F21: P0 | G21: 1 | H21: Correctness-critical | I21: INFRA | J21: 1 | K21: none | L21: None | M21: None | N21: 1 | O21: None | P21: None | Q21: 100 | R21: 6 | S21: As a developer, I want the database/Redis configuration, the Alembic environment and the container test fixtures to exist, so that E01-S01 can start writing migrations instead of first building the ground they run on. | T21: 1. DatabaseConfig + RedisConfig in common/config.py; database:/redis: sections in system.yaml 2. alembic.ini + migrations/env.py wired to load_config(), with the TimescaleDB chunk filter on autogenerate 3. common/db/base.py — DeclarativeBase + constraint naming convention 4. common/db/eventloop.py — Windows ProactorEventLoop fix for async psycopg 5. .env.example credential split; docker-compose DATABASE_URL/REDIS_URL injection; Makefile --env-file fix 6. tests/conftest.py container fixtures + 6 scaffold integration tests | U21: • `alembic upgrade head` runs (and fails with a helpful message when no password is configured) • Container fixtures start TimescaleDB + Redis and SKIP rather than fail when Docker is down • `doctor` reports which datastore config source is in effect • Test container image is read from docker-compose so it cannot drift • Full suite green | V21: CLOSED — completed 7 Aug 2026, ahead of E01-S01. Added retrospectively: this work was NOT in the backlog, but E01-S01 task 1 assumed all of it existed. Recording it so the 2-day E01-S01 estimate is not silently carrying another day of work. FOUR BLOCKERS FOUND BY EXECUTION, each of which would have stopped E01-S01 on day one: 1. async psycopg refuses Windows' default ProactorEventLoop — `make migrate` failed outright with InterfaceError. Invisible on Linux/macOS, so CI would never have caught it. 2. `make up` never passed compose an --env-file, so it failed even with a correct .env. 3. GRAFANA_PASSWORD required by compose but missing from .env.example. 4. `make` is not installed on this machine at all. Result: 118 tests passing (112 + 6 new). See Code/SETUP.md. | W21: Verified empirically rather than from docs: • TimescaleDB 2.17.2 has add_compression_policy only; 2.29.1 has BOTH that and add_columnstore_policy — so the pin upgrade is backward compatible. Registry says 2.29.1 is current (a web source claiming 2.20.2 was stale). • TA-Lib resolved to a prebuilt Windows wheel (0.7.1) — NOT the install blocker it appeared to be. • testcontainers: .postgres/.redis import paths are deprecated (use .community.*), and PostgresContainer defaults to driver='psycopg2' which this project does not install.
A22: E01-S08 | B22: E01 | C22: PERSISTENCE & DATA LAYER | D22: Clear lint debt so `make check` can gate merges | E22: Closed | F22: P1 | G22: 1 | H22: Low | I22: INFRA | J22: 0.5 | K22: none | L22: None | M22: None | N22: 1 | O22: None | P22: None | Q22: 100 | R22: 4 | S22: As a developer, I want `make check` to exit 0 on a clean tree, so that it can be used as a merge gate for E01 instead of being a command everyone knows is already red. | T22: 1. `ruff check --fix .` — clears 14 of 30 automatically 2. `ruff format .` 3. Fix the remainder by hand: line length, ambiguous Unicode in docstrings, unused noqa directives, one assert_raises_exception, one hardcoded-password-string (test fixture — confirm it is a false positive before silencing) 4. Confirm `make check` exits 0, then treat any future failure as a genuine regression | U22: • `ruff check .` reports no errors • `ruff format --check .` reports no changes needed • `make check` (lint + types + tests) exits 0 • No test is deleted or skipped to achieve the above | V22: CLOSED 7 Aug 2026. `make check` (lint + types + tests) now exits 0 — the merge gate works. Was 28 ruff errors + 1 mypy error. Auto-fix cleared 12; the rest were fixed individually: an S105 false positive on an auth-method NAME, RUF012 needing ClassVar, RUF043 needing a raw regex, B017 blind pytest.raises(Exception) narrowed to ValidationError, __all__ sorted, one stale type: ignore removed. CONFIG DECISION: RUF001/002/003 confusables are configured via allowed-confusables rather than mangled. En dashes, ≤/≥ and ₹ are deliberate typography throughout the docs; rewriting them to ASCII would make the documentation worse. Anything NOT on the allowlist is still flagged, so a Cyrillic homoglyph in an identifier is still caught. Done FIRST rather than last (the story originally said 'before E01-S01 merges'): a green gate from day one benefits every story after it. | W22: Sequence before E01-S01 merges, not before it starts — the two are independent and this one needs no design decisions. Half a day is generous; most of it is one command.
A23: E02-S01 | B23: E02 | C23: BROKER INTEGRATION | D23: Kite Connect authentication — redirect flow | E23: Development Completed | F23: P0 | G23: 1 | H23: Safety-critical | I23: SEC | J23: 2 | K23: none | Q23: 0.9 | R23: 7 | S23: As a trader, I want the daily Zerodha login to complete through a link I tap on my phone, so that the system has a valid session before pre-open without me sitting at a laptop. | T23: 1. Generate the Kite login URL with `api_key` 2. Local callback endpoint receiving `request_token` 3. Exchange `request_token` + `api_secret` → `access_token` 4. Store token as `SecretString` in Redis with TTL to next pre-open 5. Send the login link via Telegram at the configured time 6. Confirm success back to Telegram 7. Alert loudly on failure — this blocks the trading day | U23: • Full flow completes from a phone in under 60 seconds • Token never appears in any log • Expired token is detected before the pre-market job starts | V23: Auth manager, session lifecycle, login-URL builder AND the client factory are built and tested. session.py now completes the redirect login: build_client() and exchange_request_token(). The raw token is revealed at exactly two points, both handing it straight to the SDK, with a test that fails if a third appears. SECURITY: the re-auth notice carries NO login link - ReauthNotice has no url field at all, so the phishing reflex cannot be reintroduced by a later edit. The api_key is validated before it reaches the login URL (QA-SEC-15): unvalidated, an injected redirect_uri steers your request_token to an attacker while you are on a genuine Zerodha page. Remaining 10%: verifying the exchange against a live request_token, and the callback endpoint - which is the same network decision as E17-S01's dashboard access (localhost vs phone). Decide them together. | X23: TWO issues. (1) Task 5 sends a login link over Telegram, which trains you to authenticate from an inbound message — the consent-phishing pattern. Anyone who can post one message (leaked bot token, SIM-swapped Telegram, lookalike bot) sends a link to THEIR Kite app at the time you expect it; you authenticate on a genuine Zerodha page and hand them a request_token they exchange with their own api_secret. 2FA does not help — you are authorising the wrong app, not leaking a password. Server-side nonce checks cannot help either: the attack completes entirely outside your system. FIX: send a notification with NO link; open the dashboard from your own bookmark. (2) Task 2 says 'local callback endpoint' but acceptance says 'completes from a phone'. A phone cannot reach 127.0.0.1 on the server. Either the callback is publicly reachable over HTTPS — which puts an inbound endpoint on the box holding broker credentials, against the internal-network design — or the flow completes on the server host. Decide before building.
A24: E02-S02 | B24: E02 | C24: BROKER INTEGRATION | D24: Session lifecycle and daily re-auth scheduling | E24: Development Completed | F24: P0 | G24: 1 | H24: Safety-critical | I24: SEC | J24: 1 | K24: E02-S01 | Q24: 0.7 | R24: 5 | S24: As a compliance-conscious operator, I want sessions to expire and re-establish daily, so that the SEBI auto-logout requirement is met by design. | T24: 1. Scheduled trigger at `broker.auth.daily_reauth_time` 2. Session validity check before every trading-day transition 3. Retry with backoff ×3, then halt the day 4. `auth.refreshed` / `auth.failed` events 5. Health gate integration — no valid session means no trading | U24: • 20 consecutive sessions authenticate successfully • A failed auth prevents the session reaching `TRADING` | V24: Session validity, expiry-at-next-reauth and the notice hook are built and tested. Remaining: wiring the scheduled trigger and the health gate, which belong to the orchestrator rather than the broker layer.
A25: E02-S03 | B25: E02 | C25: BROKER INTEGRATION | D25: Read-only market data adapter | E25: QA-Success | F25: P0 | G25: 1 | H25: Correctness-critical | I25: FEAT | J25: 1.5 | K25: E02-S01 | Q25: 1 | R25: 4 | S25: As a developer, I want a read-only Kite adapter, so that data services physically cannot place orders. | T25: 1. Implement `MarketDataAdapter` for Kite 2. `fetch_instruments`, `fetch_historical`, quote endpoints 3. Apply `ReadOnlyGuard` so trading methods raise 4. Map Kite errors to the adapter's error taxonomy | U25: • Calling `place_order` on this adapter raises `PermissionError` • Data endpoints work from a non-whitelisted IP (verifying the order-only scope) | V25: Read-only adapter built on ReadOnlyGuard; place/modify/cancel all raise PermissionError, asserted. subscribe() deliberately raises: E05-S01 will implement the documented Kite WebSocket wire protocol rather than KiteTicker, which avoids autobahn 19.11.2 (CVE-2020-35678, blocker B7) and the Twisted reactor bridging problem in one move. Needs no static IP - Zerodha validates the whitelist on order endpoints only.
A26: E02-S04 | B26: E02 | C26: BROKER INTEGRATION | D26: Trading adapter with market protection | E26: QA-Success | F26: P0 | G26: 5 | H26: Safety-critical | I26: FEAT | J26: 2 | K26: E02-S03, E14-S01 | Q26: 1 | R26: 7 | S26: As a trader, I want orders placed correctly with market protection attached, so that MARKET and SL-M orders are not rejected by the broker. | T26: 1. Implement `TradingAdapter` for Kite 2. Attach `market_protection` on MARKET/SL-M 3. Attach Algo-ID per the confirmed mechanic (blocked on B1) 4. `place_order`, `modify_order`, `cancel_order` 5. `fetch_orderbook`, `fetch_positions`, `find_by_client_order_id` 6. Map broker errors → `OrderRejectedError` / `AmbiguousOrderError` / `RateLimitError` 7. Verify installed SDK exposes `market_protection`, fail startup if not | U26: • A MARKET order without protection is impossible to construct • A timeout raises `AmbiguousOrderError`, never a silent retry | V26: Trading adapter with market protection enforced at the boundary (missing and zero both refused). client_order_id -> Kite tag resolved: the tag is alphanumeric, max 20 chars, and IS returned in the orderbook, so broker_tag() truncates the sha256 id deterministically in one place and the submission and recovery paths are asserted to agree. Restructured so the trading adapter does NOT inherit ReadOnlyGuard - 'may trade' is stated positively rather than achieved by overriding a refusal. | X26: RESOLVED Aug 2026. Kite's tag is alphanumeric, max 20 chars, and IS returned in the orderbook - confirmed against the API docs. broker_tag() truncates the sha256 id deterministically in one place, and a test asserts the submission and recovery paths produce the same value. A non-alphanumeric id is refused rather than silently mangled. Two further defects were found here by QA and fixed: a foreign order type used to kill the whole orderbook read (QA-E02-01), and a duplicate tag used to be resolved by picking one (QA-E02-02).
A27: E02-S05 | B27: E02 | C27: BROKER INTEGRATION | D27: Order rate limiting | E27: QA-Success | F27: P0 | G27: 5 | H27: Safety-critical | I27: SEC | J27: 1 | K27: E01-S03, E02-S04 | Q27: 1 | R27: 5 | S27: As a compliance-conscious operator, I want the order rate capped in the adapter, so that no caller can breach the limit regardless of its behaviour. | T27: 1. Redis token bucket wrapping `place_order` 2. Separate bucket for data endpoints 3. Backpressure: queue with depth limit 4. Reject new signals rather than delay orders unboundedly 5. `orders_rate_limited_total` metric | U27: • A deliberate flood of 100 orders/sec results in ≤ 3/sec reaching the broker • Queue depth beyond threshold rejects rather than buffers | V27: Redis token bucket, account-wide key, orders and data on separate budgets so a backfill cannot starve an exit. Refuses rather than queues. Config refuses >= 10 orders/sec in code. FOUND A REAL DEFECT while testing this - see QA-SEC-14. | X27: RESOLVED Aug 2026, and CONFIRMED by Zerodha: ten OPS is account-specific, regardless of the number of apps. The bucket is account-scoped in Redis, orders and data have separate budgets so a backfill cannot starve an exit, and the config refuses ten or more per second in code. STILL LIVE: the budget is shared with anything else trading the account, including the Kite mobile app. Running at 3/sec against a cap of 10 leaves that headroom deliberately - but manual trading during a session eats into it.
A28: E02-S06 | B28: E02 | C28: BROKER INTEGRATION | D28: Instrument master synchronisation | E28: QA-Success | F28: P0 | G28: 1 | H28: Correctness-critical | I28: FEAT | J28: 1 | K28: E01-S02, E02-S03 | Q28: 1 | R28: 4 | S28: As a system, I need the current instrument master, so that symbols map to broker tokens, lot sizes and tick sizes correctly. | T28: 1. Daily fetch of the instrument dump 2. Upsert into `instruments` 3. Detect and log symbol changes, delistings, new listings 4. Tick-size rounding helper verified against real instruments | U28: • A limit price is always snapped to a valid tick before submission | V28: Instrument sync with new-listing and delisting detection, and an implausibility check so a truncated download is loud rather than silently shrinking the universe. Side-aware tick rounding added: buy rounds down, sell rounds up, so neither side ever pays more than intended. | X28: RESOLVED Aug 2026, and it was worse than this concern described. Side-aware rounding was written and tested (buy down, sell up, so neither side pays more than intended) - and then never called in the order path. The BA pass caught it: E02-S06's acceptance criterion says a limit price is ALWAYS snapped, and ATR-derived stops are essentially never on a 0.05 grid, so the exchange would have rejected every computed stop. Now snapped at the boundary, trigger prices too, failing CLOSED when no tick resolver is wired.
A29: E02-S07 | B29: E02 | C29: BROKER INTEGRATION | D29: Live margin retrieval | E29: QA-Success | F29: P0 | G29: 5 | H29: Safety-critical | I29: FEAT | J29: 0.5 | K29: E02-S04 | Q29: 1 | R29: 3 | S29: As a risk engine, I need real available margin from the broker, so that sizing never assumes leverage that SEBI peak-margin rules do not permit. | T29: 1. `fetch_margins` returning `MarginSnapshot` 2. Cache with a short TTL (margin moves during the session) 3. Staleness guard — reject sizing on stale margin data | U29: • Sizing uses live margin, never a computed leverage multiple | V29: Live margin plus a staleness bound. margin_for_sizing() refuses a snapshot older than the TTL, which closes the time-of-check/time-of-use gap - margin falls after every fill, so a stale reading can authorise a position the account cannot carry. | X29: RESOLVED Aug 2026. margin_for_sizing() refuses a snapshot older than the TTL, closing the time-of-check/time-of-use gap - margin falls after every fill, so a stale reading can authorise a position the account cannot carry. NOTE the bound is on AGE, not on change. Re-fetching after each fill is the caller's responsibility and belongs with E14-S06.
A30: E02-S08 | B30: E02 | C30: BROKER INTEGRATION | D30: Fallback broker adapter (Fyers) | E30: New | F30: P2 | G30: 2 | H30: Low | I30: FEAT | J30: 2 | K30: E02-S03 | R30: 3 | S30: As an operator, I want a second data source, so that a Zerodha WebSocket outage at the open does not blind the system. | T30: 1. Fyers auth and read-only adapter 2. Failover logic on primary feed staleness 3. Cross-source price divergence detection | V30: DEFERRED, not blocked. Fyers fallback is the only Low-risk story in E02 and adds a second broker SDK plus a second auth flow. Worth doing once the primary path has run against live data, so the fallback is written against known behaviour rather than assumptions.
A31: E02-S09 | B31: E02 | C31: BROKER INTEGRATION | D31: Broker error taxonomy handling | E31: QA-Success | F31: P0 | G31: 5 | H31: Safety-critical | I31: FEAT | J31: 1 | K31: E02-S04 | Q31: 1 | R31: 5 | S31: As a system, I want every broker failure classified correctly, so that an ambiguous outcome never results in a duplicate order. | T31: 1. Map every Kite error code to the taxonomy 2. `AmbiguousOrderError` → query-by-`client_order_id` recovery path 3. Never retry on `OrderRejectedError` 4. Exponential backoff on `RateLimitError` 5. Log every unmapped error code loudly for triage | U31: • Simulated timeout + reconnect produces exactly one position (chaos test) | V31: Error taxonomy with the safety switch: classify(mutating=True) makes any UNRECOGNISED failure AmbiguousOrderError, routing to query-by-tag rather than retry. Only a 429 is retryable. Verified by mutation testing - breaking the fail-closed rule fails the test. | X31: RESOLVED Aug 2026. classify(mutating=True) makes ANY unrecognised failure AmbiguousOrderError, routing to query-by-tag rather than a retry; only a 429 is retryable. Verified by mutation testing - breaking the fail-closed rule fails the test. The default disposition for an unknown code is now the safe one rather than an unspecified one.
A32: E03-S01 | B32: E03 | C32: HISTORICAL DATA | D32: NSE bhavcopy fetcher and archiver | E32: New | F32: P0 | G32: 1 | H32: Correctness-critical | I32: FEAT | J32: 1.5 | K32: E01-S02 | R32: 6 | S32: As a system, I need daily EOD data stored locally, so that pre-market analysis does not depend on a rate-limited API every morning. | T32: 1. Download bhavcopy for a given date 2. Parse and normalise to the `Bar` model 3. Idempotent upsert (re-running a date is safe) 4. Backfill utility for a date range 5. Handle holidays and missing files gracefully 6. Schedule at 05:30 | U32: • Backfilling 2 years completes and is re-runnable without duplicates | X32: NSE replaced the legacy bhavcopy with the UDiFF format and moved the URL. A fetcher written against the old path will 404, or worse fetch a stale mirror. Pin the exact source and assert on the header row, not just on HTTP 200. Also: bhavcopy is UNADJUSTED, so this must land before E03-S02 computes factors, never after.
A33: E03-S02 | B33: E03 | C33: HISTORICAL DATA | D33: Corporate action adjustment | E33: Development Completed | F33: P0 | G33: 1 | H33: Safety-critical | I33: FEAT | J33: 2 | K33: E03-S01 | L33: Feed only — B1/B4 (broker data source). Engine is complete. | Q33: 0.7 | R33: 5 | S33: As an analyst, I want historical prices adjusted for splits and bonuses, so that moving averages do not show phantom breakouts. | T33: 1. Fetch corporate action data — NOT DONE, needs a data source (see Blocked By) 2. [DONE] Store actions in `corporate_action` — the source of truth for adjustment 3. [DONE] Derive `price_adj_factor` / `volume_adj_factor` per bar; raw OHLC never mutated 4. [DONE] Re-adjustment when a new action is announced — full recompute, idempotent 5. [DONE] Verify against a known historical split | U33: • A known 1:5 split produces a continuous price series across the event • 🔴 Unadjusted data can never reach the indicator engine | V33: DESIGN BLOCKER RESOLVED 11 Aug 2026. See SPRINT02_TECHNICAL_SPEC.md §4 and CA-B1 on the Blockers sheet. THE BLOCKER: the schema specified `ohlcv.is_adjusted BOOLEAN`, which cannot support re-adjustment. When a second action arrives you need the factor ALREADY APPLIED in order to apply the next one, and a boolean does not carry it. Adjusting prices in place compounds silently — no exception, no failing test, just a permanently wrong price history. This is safety-critical because a wrong adjustment does not fail loudly; every backtest over the affected symbol simply becomes fiction. THE RESOLUTION: raw prices are never modified. A new `corporate_action` table is the source of truth, and each bar carries two derived factors — adjusted price = raw * price_adj_factor. Recompute always rebuilds from the FULL action history, which makes it idempotent, and makes a mis-entered action fixable by correcting its row and recomputing. TWO factors, not one: a dividend reduces price but leaves volume untouched, so a single reciprocal factor would corrupt volume on every dividend — and volume feeds both the liquidity filter and the volume-ratio indicator. BR-16 IS ENFORCED STRUCTURALLY, not by convention: BarRepository has no method that returns raw prices. The only accessor is `raw_bars_for_audit`, named to be hard to reach for, and a test asserts no raw-read sibling exists. The trading path cannot ask for unadjusted data by accident. | W33: 18 tests, all passing. Three findings came out of building it, each now covered by its own test: 1. ORDER INDEPENDENCE WAS ONLY APPROXIMATE. A Hypothesis property test caught that multiplying Decimal QUOTIENTS is not exactly associative — combining the same three splits in two different orders gave answers differing in the last digits. Fixed by keeping factors as exact ratios (numerator/denominator held separately) and dividing once at the end. Actions arrive from a feed in arbitrary order, so this had to be exact rather than nearly exact. 2. RESTORE FROM ARCHIVE MISSED ADJUSTMENTS. Archived bars are not in `ohlcv`, so any action recorded while they were away updated the live bars and skipped them. Restoring them would have spliced an unadjusted segment onto an adjusted series. `restore_bars` now recomputes factors for every restored symbol. 3. CONCURRENT RECOMPUTE COULD LOSE AN ACTION. Two recomputes for one symbol could interleave and the older action set could win. Row locks do not catch this because both writers are self-consistent. Now takes a per-symbol transaction-scoped advisory lock before reading, same pattern as the audit chain. ALSO: dividends are recorded but NOT applied to prices (APPLY_DIVIDEND_ADJUSTMENT = False). These are intraday strategies that never hold across an ex-date, and dividend adjustment rewrites every historical price. Flip it only alongside a decision about what backtests are measuring.
A34: E03-S03 | B34: E03 | C34: HISTORICAL DATA | D34: Intraday history backfill | E34: New | F34: P0 | G34: 1 | H34: Correctness-critical | I34: FEAT | J34: 1.5 | K34: E02-S03 | R34: 4 | S34: As a backtester, I need minute-level history, so that strategies can be validated on realistic intraday data. | T34: 1. Paged historical fetch respecting rate limits 2. Backfill orchestration across the universe 3. Resume from interruption 4. Progress reporting (this takes hours) | X34: PARTLY RESOLVED Aug 2026. Blocker B4 is gone: historical data is no longer a separate paid add-on. The free Personal tier carries NO data; Connect at Rs.500/month bundles real-time WebSocket AND historical candles. So this story needs a Rs.500 subscription, not Rs.2500. STILL LIVE: the rate limit and the per-request date-range cap remain, and a multi-hour backfill during market hours competes with live data on the same account-wide budget. Schedule it outside the session.
A35: E03-S04 | B35: E03 | C35: HISTORICAL DATA | D35: Data quality validation | E35: New | F35: P0 | G35: 1 | H35: Correctness-critical | I35: TEST | J35: 1.5 | K35: E03-S01 | R35: 5 | S35: As a developer, I want stored data validated, so that silent corruption is caught before it reaches analysis. | T35: 1. Gap detection (missing sessions, missing bars within a session) 2. OHLC coherence check across the whole store 3. Volume sanity (zero-volume bars flagged) 4. Price continuity (unexplained jumps beyond circuit limits) 5. Report generated after every sync | U35: • A deliberately corrupted row is reported by the next validation run | X35: 'Unexplained jumps beyond circuit limits' will fire on every split and bonus, because a raw price series is SUPPOSED to gap at an ex-date. The check must join corporate_action and treat an explained jump as clean — otherwise every corporate action raises a false alarm and the report stops being read.
A36: E03-S05 | B36: E03 | C36: HISTORICAL DATA | D36: Multi-timeframe aggregation from stored data | E36: New | F36: P0 | G36: 2 | H36: Correctness-critical | I36: FEAT | J36: 1 | K36: E03-S01 | R36: 3 | S36: As the pre-market job, I need higher timeframes derived from daily data, so that weekly and monthly analysis is available without separate downloads. | T36: 1. Aggregate daily → weekly with correct session boundaries 2. Handle partial weeks at period edges 3. Verify aggregation against broker-supplied weekly bars | X36: 'Verify against broker-supplied weekly bars' only holds if both sides use the same adjustment basis. Kite's weekly bars are adjusted; ours are raw-plus-factor. Compare adjusted-to-adjusted, or the check fails for every symbol that ever had a corporate action.
A37: E03-S06 | B37: E03 | C37: HISTORICAL DATA | D37: Tick archival to Parquet | E37: New | F37: P2 | G37: 6 | H37: Low | I37: OPS | J37: 0.5 | K37: E05-S01 | R37: 0 | S37: As a developer, I want raw ticks archived, so that the replay harness can reproduce a session exactly.
A38: E04-S01 | B38: E04 | C38: INDIA HAZARD LISTS | D38: ASM/GSM surveillance list fetcher | E38: New | F38: P0 | G38: 1 | H38: Safety-critical | I38: FEAT | J38: 1 | K38: E01-S02 | R38: 5 | S38: As a risk-aware trader, I want surveillance-listed stocks excluded, so that I never trade a name carrying 100% margin or reduced circuit bands. | T38: 1. Fetch ASM (short-term and long-term) lists 2. Fetch GSM list with stage 3. Upsert into `instrument_daily_status` 4. Alert on newly-added names currently held 5. Handle source-format changes without silent failure | U38: • A stock added to ASM overnight is excluded from today's universe • 🔴 A fetch failure blocks the trading day rather than proceeding blind | X38: Publication time matters more than the schedule. NSE posts these lists at varying times; a 05:30 fetch may retrieve yesterday's file under today's name. Assert the file's OWN effective date, not the fetch time. Also use gsm_stage, not just the boolean — stage 4 is periodic call auction with no upward movement, a completely different hazard from stage 1, and the schema now carries the stage for exactly this reason.
A39: E04-S02 | B39: E04 | C39: INDIA HAZARD LISTS | D39: T2T (Trade-to-Trade) list | E39: New | F39: P0 | G39: 1 | H39: Safety-critical | I39: FEAT | J39: 0.5 | K39: E01-S02 | R39: 3 | S39: As a trader, I want T2T stocks excluded absolutely, so that I never place an intraday order that becomes an unintended delivery obligation. | T39: 1. Fetch the T2T segment list 2. Mark `is_t2t` in daily status 3. Hard filter — not configurable (config validation already enforces this) | U39: • 🔴 No T2T symbol can reach the watchlist under any configuration
A40: E04-S03 | B40: E04 | C40: INDIA HAZARD LISTS | D40: F&O ban list | E40: New | F40: P0 | G40: 1 | H40: Safety-critical | I40: FEAT | J40: 0.5 | K40: E01-S02 | R40: 3 | S40: As a trader, I want ban-period stocks flagged, so that I avoid a penalty of 1% of position value (min ₹5,000, max ₹1,00,000). | T40: 1. Fetch the daily ban list 2. Mark `is_fno_ban` 3. Exclude from F&O trading; flag (not exclude) for equity
A41: E04-S04 | B41: E04 | C41: INDIA HAZARD LISTS | D41: Circuit bands and price limits | E41: New | F41: P0 | G41: 1 | H41: Correctness-critical | I41: FEAT | J41: 1 | K41: E01-S02 | R41: 4 | S41: As a trader, I want per-stock circuit bands known, so that narrow-band stocks are excluded and orders never target an unreachable price. | T41: 1. Fetch band percentages per symbol 2. Compute upper/lower circuit prices from previous close 3. Filter by `min_circuit_band_pct` 4. Reject orders outside band at validation time
A42: E04-S05 | B42: E04 | C42: INDIA HAZARD LISTS | D42: CAS classification | E42: New | F42: P0 | G42: 1 | H42: Safety-critical | I42: FEAT | J42: 1 | K42: E01-S02 | R42: 4 | S42: As a position manager, I need to know which stocks are in CAS scope, so that each position uses the correct square-off deadline. | T42: 1. Determine CAS-scope (Category I / F&O) symbols 2. Mark `is_cas_stock` 3. Wire into `MarketCalendar.squareoff_deadline` 4. Alert on classification changes | U42: • 🔴 A CAS stock's deadline is 15:10, a non-CAS stock's is 15:20, per position | X42: The deadline must be pinned at position OPEN and stored with the position, never recomputed at exit time from current classification. If NSE reclassifies a symbol during the day, a recomputed deadline could move LATER and put you past the broker's square-off. E15-S06 computes at open — make sure this story feeds that path, not the exit path.
A43: E04-S06 | B43: E04 | C43: INDIA HAZARD LISTS | D43: Earnings and corporate action calendar | E43: New | F43: P1 | G43: 1 | H43: Correctness-critical | I43: FEAT | J43: 1 | K43: E01-S02 | R43: 4 | S43: As a trader, I want earnings-day stocks excluded, so that a technical thesis is not invalidated by a binary event. | T43: 1. Fetch results calendar 2. Fetch dividend/split/bonus announcements 3. Mark `has_earnings_today` 4. Configurable exclusion window (before/after)
A44: E04-S07 | B44: E04 | C44: INDIA HAZARD LISTS | D44: NSE holiday calendar — complete it | E44: New | F44: P0 | G44: 1 | H44: Safety-critical | I44: OPS | J44: 1 | K44: none · **carried debt** | R44: 5 | S44: As a system, I need the complete NSE holiday list, so that I do not treat a market holiday as a trading day. | T44: 1. Transcribe the full NSE holiday circular into `nse_holidays.yaml` 2. Set `verified_against_nse_circular: true` 3. Decide Diwali Muhurat session policy (default: stand down) 4. Annual refresh reminder documented in the runbook 5. Consider automated fetch with manual verification | U44: • 🔴 `make doctor` reports the calendar as verified • Every holiday in the circular is excluded by `is_trading_day` | V44: DATED, 27 Oct 2026: config/nse_holidays.yaml covers 2026 only. MarketCalendar fails CLOSED on an uncovered year (HolidayDataError), so from 1 Jan 2027 the system refuses to trade until the 2027 list is added. NSE publishes it in December; add it, triangulated against two publications as the 2026 list was, before the last trading day of 2026. | X44: The Muhurat session is the trap: Diwali is a holiday on which the exchange runs a special ~1-hour evening session. A calendar with one session per day cannot express it. 'Stand down' is the right default, but record it as a DECISION — otherwise someone later 'fixes' the calendar and the system trades a session it was never tested against.
A45: E05-S01 | B45: E05 | C45: MARKET DATA INGESTION | D45: WebSocket client with reconnection | E45: QA-Success | F45: P0 | G45: 1 | H45: Correctness-critical | I45: FEAT | J45: 2 | K45: E02-S03 | Q45: 0.85 | R45: 6 | S45: As a system, I want a resilient tick stream, so that a dropped connection does not silently stop the market data flow. | T45: 1. KiteTicker integration with async bridging 2. Subscribe/unsubscribe for the day's watchlist 3. Exponential backoff reconnection 4. On reconnect: mark indicator state STALE, do not resume silently 5. Heartbeat monitoring with staleness detection 6. Rebuild the in-progress bar from a REST snapshot after a gap | U45: • A 5-minute forced disconnect recovers and flags the gap • 🟠 Indicators are marked stale rather than computing across the hole | V45: WebSocket client built on the `websockets` library, NOT KiteTicker - which resolves blocker B7 and the Twisted-to-asyncio bridging problem together. Wire protocol implemented from the documented byte-level spec: frame splitting, ltp/quote/full packets, index packets, market depth. Reconnection with capped exponential backoff and jitter; a connection that survives 60s resets the backoff so one bad hour does not pin it at maximum all day. Every reconnect emits a FeedGap BEFORE any tick that follows, so downstream marks indicators stale rather than computing across a hole. Connections open inside `async with` so a reconnect cannot leak one and exhaust Kite's 3-connection cap. An idle socket (no frame for 45s) is treated as dead - the failure a TCP check reports healthy. REMAINING 15%: the connection itself needs live credentials, and one real packet per mode must be captured and asserted against. The parser is verified self-consistent (tests build packets to the same spec they parse) which proves it matches the SPEC, not that the spec matches the exchange. | X45: RESOLVED Aug 2026 - and it resolved blocker B7 at the same time. Built on the `websockets` library rather than KiteTicker, so autobahn 19.11.2 (CVE-2020-35678) is never imported and there is no Twisted reactor to bridge. Connection-leak and reconnect-storm hazards both addressed explicitly. STILL LIVE: the packet offsets are verified SELF-CONSISTENTLY only. Capture one real packet per mode and assert against it before this feeds anything that trades - a transposed field produces plausible numbers, which is the failure that survives review.
A46: E05-S02 | B46: E05 | C46: MARKET DATA INGESTION | D46: Tick validation | E46: QA-Success | F46: P0 | G46: 1 | H46: Correctness-critical | I46: FEAT | J46: 1 | K46: E05-S01 | Q46: 1 | R46: 5 | S46: As a data pipeline, I want malformed ticks rejected at the edge, so that nothing downstream has to defend against them. | T46: 1. Reject null/zero/negative price 2. Reject negative volume 3. Reject timestamp outside ±5s of local clock (broker clock skew) 4. Metric per rejection reason 5. Log rejections — a cluster indicates a feed problem | V46: Null/zero/negative price, negative volume, and clock skew beyond 5s all refused. Added beyond the story: session volume going BACKWARDS is refused - cumulative volume cannot fall, so a decrease means a replayed or out-of-order packet, and accepting it makes every volume-delta negative. Every rejection counted by reason with a bounded sample.
A47: E05-S03 | B47: E05 | C47: MARKET DATA INGESTION | D47: Deduplication | E47: QA-Success | F47: P0 | G47: 1 | H47: Correctness-critical | I47: FEAT | J47: 0.5 | K47: E05-S02 | Q47: 1 | R47: 3 | S47: As a data pipeline, I want duplicate ticks dropped, so that WebSocket replay after a reconnect does not double-count volume. | T47: 1. Bounded LRU per symbol on (symbol, exchange_ts, ltp, volume) 2. Size-capped to bound memory 3. Metric for duplicates dropped | V47: Bounded LRU per instrument on (exchange_ts, ltp, volume, last_qty). Per-instrument rather than global so one busy symbol cannot evict a quiet one's history - tested explicitly.
A48: E05-S04 | B48: E05 | C48: MARKET DATA INGESTION | D48: Outlier filtering | E48: QA-Success | F48: P0 | G48: 1 | H48: Safety-critical | I48: FEAT | J48: 1 | K48: E05-S03 | Q48: 1 | R48: 4 | S48: As an analyst, I want bad prints rejected, so that one erroneous tick does not permanently corrupt an EMA. | T48: 1. Reject if move exceeds `max(5 × ATR%, 2%)` 2. Cross-check against circuit limits — a price outside them is impossible 3. Log rather than silently drop 4. Alert on a cluster of rejections for one symbol | U48: • 🔴 A single injected bad print does not change any indicator value | V48: THE COLD-START GAP IS CLOSED. The bound is max(5 x ATR%, 2%), but ATR does not exist at 09:15 - exactly when prints are most erratic. A missing ATR resolving to 'no limit' would leave the filter inert when it matters most. It resolves to the 2% floor instead, and cold_start() reports the condition so a health panel can show it. Circuit band checked independently and applies even to the first tick, where there is no previous price. A rejected outlier does NOT move the baseline - otherwise a second bad print would look reasonable. | X48: RESOLVED Aug 2026. The cold-start behaviour is now explicit rather than implied: no ATR means the 2% floor applies on its own, and OutlierFilter.cold_start() exposes the condition so it can be asserted in a test and shown on a health panel. Four tests cover the window specifically.
A49: E05-S05 | B49: E05 | C49: MARKET DATA INGESTION | D49: Normalisation | E49: QA-Success | F49: P0 | G49: 1 | H49: Correctness-critical | I49: FEAT | J49: 0.5 | K49: E05-S04 | Q49: 1 | R49: 3 | S49: As a developer, I want broker payloads converted to canonical types at the boundary, so that no broker-specific shape leaks downstream. | T49: 1. Kite payload → `Tick` model 2. All timestamps → UTC 3. All prices → `Decimal` | V49: RawTick -> domain Tick, running LAST so a tick that failed any check never becomes a domain object. Prices exact via Decimal from integer paise.
A50: E05-S06 | B50: E05 | C50: MARKET DATA INGESTION | D50: Bar builder with session alignment | E50: QA-Success | F50: P0 | G50: 1 | H50: Safety-critical | I50: FEAT | J50: 2 | K50: E05-S05 | Q50: 1 | R50: 5 | S50: As an analyst, I want bars aligned to the session start, so that a 15-minute bar runs 09:15–09:30 and indicators are not silently offset. | T50: 1. In-progress bar per (symbol, timeframe) 2. Boundary detection via `MarketCalendar.bar_open_time` 3. Seal and publish on boundary crossing 4. Emit in-progress updates with `is_final=False` 5. Cascade 1m → 5m → 15m → 1h within the builder | U50: • 🔴 Bar boundaries match the calendar exactly across a full session • Consumers can distinguish final from in-progress bars | V50: Bars align to the SESSION start, delegating to MarketCalendar.bar_open_time so there is one definition of a boundary. Timeframes built INDEPENDENTLY from ticks rather than cascaded - cascading means one bad 1m bar propagates silently into every higher timeframe. Bar volume is the DELTA of cumulative session volume, not the raw total. A sealed bar NEVER mutates: a late tick is dropped and counted, because the opening range is sealed at 09:30 and levels derived from it are already sizing positions. CAS-scope bars covering the 15:15 call auction are marked. | X50: RESOLVED Aug 2026. Timeframes are built independently from ticks rather than cascaded, so a defect in the 1m path cannot reappear in the hourly series. CAS-window bars are marked. Late ticks are dropped and counted rather than mutating a sealed bar.
A51: E05-S07 | B51: E05 | C51: MARKET DATA INGESTION | D51: Synthetic bar handling | E51: QA-Success | F51: P0 | G51: 1 | H51: Correctness-critical | I51: FEAT | J51: 0.5 | K51: E05-S06 | Q51: 1 | R51: 3 | S51: As an analyst, I want no-trade intervals marked, so that indicators do not treat a data gap as a price move. | T51: 1. Carry-forward bar when no trades occur 2. Flag `synthetic=True` 3. Indicator engine skips or handles synthetics explicitly | V51: Carry-forward bars flagged synthetic with zero volume. The flag is the point: an illiquid symbol printing identical bars looks like a volatility collapse to an indicator that cannot tell 'did not move' from 'did not trade'.
A52: E05-S08 | B52: E05 | C52: MARKET DATA INGESTION | D52: Quote state publishing | E52: QA-Success | F52: P0 | G52: 1 | H52: Low | I52: FEAT | J52: 0.5 | K52: E05-S05 | Q52: 1 | R52: 3 | S52: As the dashboard and risk engine, I need current quotes, so that P&L and spread checks use live prices. | T52: 1. Write `state:quote:{symbol}` on each tick 2. Include bid/ask for spread checks 3. Publish to `stream:ticks` for archival | V52: Quote state to state:quote:{symbol} with a TTL (a session key with no expiry is read next morning as live), plus optional tick archival to the stream. read_fresh() is separate from read() so staleness is an explicit caller decision rather than something silently tolerated.
A53: E06-S01 | B53: E06 | C53: TECHNICAL ANALYSIS ENGINE | D53: Incremental indicator framework | E53: QA-Success | F53: P0 | G53: 2 | H53: Safety-critical | I53: FEAT | J53: 2 | K53: E05-S06 | Q53: 1 | R53: 5 | S53: As a system, I want indicators updated in O(1) per bar, so that adding symbols does not degrade latency. | T53: 1. `Indicator` protocol: `update(bar) -> value`, `warm_up(bars)`, `is_ready` 2. TA-Lib streaming API wrapper 3. `IndicatorSet` per (symbol, timeframe) 4. State serialisation to Redis 5. Restore state on restart without full re-warm-up | U53: • 🔴 Incremental values match batch computation to 4 decimal places • 200 symbols × 6 timeframes update in < 50ms total | V53: Incremental framework with the SEEDING CONVENTION FIXED and verified by experiment, not assumed. TA-Lib emits EMA(N) first at index N-1 seeded from the simple mean of the first N; RSI and ATR use Wilder smoothing seeded from the mean of the first N samples. A streaming EMA seeded from the first value stays close forever and never equals it - which passes a 'looks right' review and fails the four-decimal acceptance criterion. Every indicator asserted against TA-Lib batch directly. | X53: RESOLVED Aug 2026, and the concern understated it. The seeding convention is now fixed AND verified by experiment against TA-Lib rather than taken from a formula. Warm-up and state-restore both use the same path, and restore-equals-rewarm is asserted for the rest of the session rather than only at the instant of restore.
A54: E06-S02 | B54: E06 | C54: TECHNICAL ANALYSIS ENGINE | D54: Core indicator implementations | E54: Development Completed | F54: P0 | G54: 2 | H54: Correctness-critical | I54: FEAT | J54: 2 | K54: E06-S01 | Q54: 1 | R54: 8 | T54: 1. EMA (20, 50, 200), SMA 2. RSI(14) 3. MACD with signal and histogram 4. ATR(14) — critical, drives position sizing 5. Bollinger Bands 6. VWAP (session-anchored) 7. Volume ratio vs 20-period average 8. ADX | U54: • Every indicator verified against a reference implementation on the same data | V54: EMA, SMA, RSI, MACD, ATR, Bollinger, VWAP, VolumeRatio - all matched to TA-Lib within 1e-4. MACD needed a real fix found by that comparison: TA-Lib seeds BOTH its EMAs at the same bar (the slow period's start), not each at its own. Composing two independent EMAs read -18.75 where TA-Lib read -20.11 on a 200-bar series - a 7% error on a line whose CROSSINGS are the signal. Bollinger uses population not sample stddev (2.6% apart at n=20). VWAP is session-anchored and ignores synthetic bars. VolumeRatio excludes the current bar so a 10x spike does not damp itself. NOT DONE: ADX. Listed in the story, deferred - it is the only one with no consumer yet.
A55: E06-S03 | B55: E06 | C55: TECHNICAL ANALYSIS ENGINE | D55: Warm-up orchestration | E55: QA-Success | F55: P0 | G55: 2 | H55: Safety-critical | I55: FEAT | J55: 1.5 | K55: E06-S01, E03-S01 | Q55: 1 | R55: 5 | S55: As a trader, I want indicators seeded from history before trading, so that a 200-EMA is never computed from 3 bars. | T55: 1. Load lookback from TimescaleDB at session start 2. Parallel warm-up in `ProcessPoolExecutor` 3. `is_ready` false until the longest-period indicator has enough data 4. Report warm-up completion per symbol 5. Block trading until the watchlist is warm | U55: • 🔴 A symbol with insufficient history is excluded, not traded on bad values | V55: Warm-up runs through the SAME code path as live updates, so the two cannot disagree - a separate batch path would only show its divergence as a discontinuity at the moment the system switched between them, mid-session. Insufficient history EXCLUDES the symbol and the report names which indicator was short, so the operator knows why a symbol left the universe. Restore-equals-rewarm is asserted, and not only at the same instant: the two must stay equal for the REST of the session, which is what catches a snapshot that captured a value but not its window. | X55: RESOLVED Aug 2026. Tested exactly as the concern asked: warm from history, snapshot, restore, compare - and then keep feeding both for another twenty bars, which is what catches a snapshot that saved the value but not the window. A snapshot from a different build is refused rather than partially applied.
A56: E06-S04 | B56: E06 | C56: TECHNICAL ANALYSIS ENGINE | D56: Multi-timeframe snapshot assembly | E56: QA-Success | F56: P0 | G56: 2 | H56: Correctness-critical | I56: FEAT | J56: 1 | K56: E06-S02 | Q56: 1 | R56: 3 | T56: 1. Assemble `MultiTimeframeSnapshot` from per-timeframe state 2. `all_ready` gate 3. Publish to Redis for `signal-engine` to read without IPC | V56: MultiTimeframeSnapshot with all_ready gating evaluation. Values are still exposed when not ready so a health panel can show what is missing rather than an unexplained refusal. A feed gap marks EVERY timeframe for that symbol stale - a 15-minute hole is a missing 5m bar and a corrupted hourly bar alike, and the hourly one is harder to notice. Staleness is NOT cleared by the next bar.
A57: E06-S05 | B57: E06 | C57: TECHNICAL ANALYSIS ENGINE | D57: Support/resistance and pivot detection | E57: QA-Success | F57: P0 | G57: 2 | H57: Correctness-critical | I57: FEAT | J57: 2 | K57: E06-S02 | Q57: 1 | R57: 5 | S57: As a strategy, I need structural levels, so that stops can be placed at points that invalidate the thesis rather than at arbitrary distances. | T57: 1. Classic pivot points (P, R1-R3, S1-S3) 2. Prior-day high/low/close 3. Swing high/low detection 4. Level clustering (nearby levels merge) 5. Level strength scoring by touch count | V57: Classic pivots, prior-day HLC, swing detection and level clustering. Clustering anchors to the first member rather than chaining, so a gently-rising staircase cannot merge into one 'level' spanning the day's range. Touches become strength, capped - a level touched twenty times is not twice as strong as one touched ten.
A58: E06-S06 | B58: E06 | C58: TECHNICAL ANALYSIS ENGINE | D58: Opening range computation | E58: QA-Success | F58: P0 | G58: 2 | H58: Safety-critical | I58: FEAT | J58: 1 | K58: E06-S02 | Q58: 1 | R58: 4 | S58: As the primary strategy, I need the 09:15–09:30 range, so that breakouts can be detected against a well-defined reference. | T58: 1. Track high/low from 09:15 to 09:30 2. Seal at 09:30 and publish 3. Compute range as % of price 4. Handle the gap-open case | U58: • 🔴 Range is sealed exactly at 09:30 and never mutates afterwards | V58: Opening range sealed at 09:30 and it NEVER moves. A late tick is refused AND COUNTED rather than silently dropped, because a silent no-op would hide a feed delivering out of order. breakout_direction() refuses to answer before sealing - answering early trades a breakout of a range still forming, which is not a breakout. An empty range is sealed-but-not-usable: a symbol that did not trade in the first fifteen minutes has no range, which is different from a narrow one. | X58: RESOLVED Aug 2026. The explicit rule the concern asked for: a tick whose exchange timestamp falls inside the window but which ARRIVES after the seal is dropped and counted. Four tests cover it, including the control that a late tick OUTSIDE the window is not an anomaly.
A59: E06-S07 | B59: E06 | C59: TECHNICAL ANALYSIS ENGINE | D59: Relative strength calculation | E59: New | F59: P0 | G59: 2 | H59: Correctness-critical | I59: FEAT | J59: 1.5 | K59: E06-S02 | R59: 4 | S59: As a scorer, I need stock-vs-sector and sector-vs-index strength, so that leaders in leading sectors rank higher. | T59: 1. Sector index mapping per symbol 2. Rolling relative performance 3. Sector-vs-Nifty ranking 4. Normalise to a 0–1 score | V59: NOT STARTED. Needs sector index mapping per symbol, which is E04-S01's data - so it waits on the NSE access question (blocker B8) rather than on anything in this epic.
A60: E06-S08 | B60: E06 | C60: TECHNICAL ANALYSIS ENGINE | D60: Chart and candlestick patterns | E60: New | F60: P2 | G60: 6 | H60: Low | I60: FEAT | J60: 1 | K60: E06-S02 | R60: 0 | V60: NOT STARTED - deliberately. Low risk, and the only E06 story with no consumer until E13 exists.
A61: E07-S01 | B61: E07 | C61: UNIVERSE & SCORING | D61: Base universe loading | E61: New | F61: P0 | G61: 2 | H61: Low | I61: FEAT | J61: 0.5 | K61: E02-S06 | R61: 4 | T61: 1. Load Nifty 50/100/200/500 constituents 2. F&O universe 3. Custom symbol list support 4. Handle index reconstitution
A62: E07-S02 | B62: E07 | C62: UNIVERSE & SCORING | D62: Hard filter pipeline | E62: New | F62: P0 | G62: 2 | H62: Safety-critical | I62: FEAT | J62: 1.5 | K62: E04 (all), E07-S01 | R62: 4 | S62: As a trader, I want structurally untradeable stocks removed before scoring, so that no ineligible name can reach an order. | T62: 1. Apply all 10 filters in order (cheapest first) 2. Record which filter excluded each symbol 3. Live preview: how many survive each filter today 4. Alert if the surviving universe is implausibly small | U62: • 🔴 Every filter in config is applied; none can be silently skipped • The exclusion reason for any symbol is queryable | X62: 'Cheapest first' makes the recorded exclusion reason ORDER-DEPENDENT — a symbol that is both T2T and illiquid is attributed to whichever check ran first. If the audit answer 'why was this excluded' matters, either record every failing filter, or document that the field means 'first failing filter', not 'the reason'.
A63: E07-S03 | B63: E07 | C63: UNIVERSE & SCORING | D63: Tradeability score components | E63: New | F63: P0 | G63: 2 | H63: Correctness-critical | I63: FEAT | J63: 2 | K63: E06-S04, E06-S07 | R63: 7 | T63: 1. Multi-timeframe trend alignment (25%) 2. Relative strength (20%) 3. Volatility fitness — scored as a *band*, not more-is-better (15%) 4. Volume expansion (15%) 5. Level proximity (15%) 6. Catalyst/news (10%) — stub until E08 7. Weighted composite, 0–100 | U63: • Weights come from config and are verified to sum to 1.0 • Each component is independently unit-tested | X63: The catalyst component is stubbed at 0 until E08, but the weights sum to 1.0 INCLUDING it. Every score is therefore depressed by 10% until news lands, and scores from before and after E08 are not comparable — which quietly invalidates E07-S06's 20-session validation report if the window spans the change. Renormalise over available components, or freeze the report window.
A64: E07-S04 | B64: E07 | C64: UNIVERSE & SCORING | D64: Ranking and shortlisting | E64: New | F64: P0 | G64: 2 | H64: Low | I64: FEAT | J64: 0.5 | K64: E07-S03 | R64: 3 | T64: 1. Rank surviving universe by score 2. Take top N (`shortlist_size`) 3. Tie-breaking rule (deterministic)
A65: E07-S05 | B65: E07 | C65: UNIVERSE & SCORING | D65: Score explainability | E65: New | F65: P0 | G65: 2 | H65: Correctness-critical | I65: FEAT | J65: 1 | K65: E07-S03 | R65: 3 | S65: As a trader, I want to see why a stock scored what it did, so that a bare number is not unaccountable. | T65: 1. Persist per-component contributions 2. Render breakdown in the UI and briefing 3. Explain rank changes day over day
A66: E07-S06 | B66: E07 | C66: UNIVERSE & SCORING | D66: Universe validation report | E66: New | F66: P1 | G66: 2 | H66: Low | I66: TEST | J66: 1.5 | K66: E07-S04 | R66: 4 | S66: As a developer, I want to compare the ranked watchlist against what actually moved, so that the scoring model can be tuned on evidence. | T66: 1. Daily: capture the ranked list 2. EOD: compare against realised ranges and volumes 3. Hit-rate metric: how often did top-10 names actually move? 4. Report over rolling 20 sessions
A67: E08-S01 | B67: E08 | C67: NEWS INTELLIGENCE | D67: News source integration | E67: New | F67: P1 | G67: 3 | H67: Correctness-critical | I67: FEAT | J67: 1.5 | K67: E01-S02 | R67: 4 | T67: 1. Allowlisted provider clients 2. Polling on `news.refresh_interval_min` 3. Per-source timeout and failure isolation 4. Raw article persistence for audit | U67: • A dead source degrades its contribution, never fails the refresh
A68: E08-S02 | B68: E08 | C68: NEWS INTELLIGENCE | D68: Near-duplicate detection and clustering | E68: New | F68: P1 | G68: 3 | H68: Correctness-critical | I68: FEAT | J68: 1.5 | K68: E08-S01 | R68: 3 | S68: As an analyst, I want syndicated copies of the same story grouped, so that one event carried by six outlets is not counted six times. | T68: 1. Similarity-based clustering 2. `cluster_id` assignment 3. Cluster size feeds salience (positively) and novelty (inversely)
A69: E08-S03 | B69: E08 | C69: NEWS INTELLIGENCE | D69: Prompt injection sanitisation | E69: New | F69: P0 | G69: 3 | H69: Safety-critical | I69: SEC | J69: 2 | K69: E08-S01 | R69: 7 | S69: As a security-conscious operator, I want news content sanitised before it reaches any prompt, so that an attacker publishing crafted content cannot steer trading decisions. | T69: 1. Strip/escape XML-ish tags and role markers 2. Detect instruction-injection phrases ("ignore previous", "system:") 3. Strip bidirectional Unicode overrides and zero-width characters 4. Length truncation 5. Set `injection_flagged` and exclude flagged articles from scoring 6. Metric per source — a rising rate is a source to drop 7. Adversarial test corpus (see E22-S06) | U69: • 🔴 Every payload in the adversarial corpus is neutralised • Flagged articles are visible in the admin UI | X69: Sanitisation and detection are different controls and the tasks mix them. Stripping tags is deterministic; detecting 'ignore previous' is a blocklist an attacker rewrites around. The REAL boundary is the structured output schema in E08-S05. Treat this as defence in depth and never let a passing sanitiser become the reason to trust article text.
A70: E08-S04 | B70: E08 | C70: NEWS INTELLIGENCE | D70: Entity resolution | E70: New | F70: P1 | G70: 3 | H70: Correctness-critical | I70: FEAT | J70: 1 | K70: E08-S02 | R70: 3 | T70: 1. Article → ticker(s) mapping 2. Sector and macro classification 3. Ambiguity handling (company names that are common words)
A71: E08-S05 | B71: E08 | C71: NEWS INTELLIGENCE | D71: AI news triage | E71: New | F71: P1 | G71: 3 | H71: Safety-critical | I71: FEAT | J71: 1.5 | K71: E08-S03, E10-S01 | R71: 4 | S71: As a system, I want structured extraction from each article, so that only bounded fields propagate downstream. | T71: 1. Haiku call with `NewsSignal` structured output 2. Event type, polarity, magnitude, certainty, horizon, scope 3. Batch articles to control cost 4. Handle refusals and schema failures by skipping the article | U71: • 🔴 No free-form field from news reaches any downstream prompt | X71: 'Batch articles to control cost' creates a cross-contamination surface: several untrusted articles in one prompt means an injection in article 3 can influence the extracted fields of articles 1 and 2. If batching, bound the batch and keep per-article outputs independently attributable — or pay for one call per article for anything that will drive a trade.
A72: E08-S06 | B72: E08 | C72: NEWS INTELLIGENCE | D72: Novelty scoring | E72: New | F72: P1 | G72: 3 | H72: Correctness-critical | I72: FEAT | J72: 1.5 | K72: E08-S05 | R72: 6 | S72: As an analyst, I want new information distinguished from echo, so that the tenth repetition of a story does not score like the first. | T72: 1. Rolling 30-day news history per symbol 2. Semantic similarity to recent articles 3. Event-type rarity for this symbol 4. Polarity surprise vs prior tone 5. Inverse cluster size 6. Weighted novelty score
A73: E08-S07 | B73: E08 | C73: NEWS INTELLIGENCE | D73: Time decay by event class | E73: New | F73: P1 | G73: 3 | H73: Correctness-critical | I73: FEAT | J73: 0.5 | K73: E08-S05 | R73: 3 | T73: 1. Exponential decay using per-class half-lives from `NewsEventType` 2. Decay measured in *trading* days, not calendar days 3. Verify a weekend does not over-decay | X73: Decay in TRADING days is right, but the trading-day count depends on the holiday calendar — the known-incomplete one (B3 / E04-S07). Until that is verified, decay silently over- or under-weights across every long weekend.
A74: E08-S08 | B74: E08 | C74: NEWS INTELLIGENCE | D74: Composite score assembly | E74: New | F74: P1 | G74: 3 | H74: Correctness-critical | I74: FEAT | J74: 1.5 | K74: E08-S06, E08-S07 | R74: 5 | T74: 1. Salience: log cluster size × source credibility × corroboration 2. Contribution = polarity × magnitude × certainty × novelty × salience × decay 3. Three separate scores — NewsScore (firm), SectorScore, MacroScore 4. Clamp to [-1, +1] 5. Stale pipeline → score 0, never last-known-value | U74: • Scores are never blended into one number • A stale pipeline is visibly stale, not silently old | X74: 'Stale pipeline -> score 0' — make sure 0 reads as NEUTRAL, not bearish, at every consumer. If one downstream treats 0 as 'no catalyst' and another as 'negative', staleness changes behaviour inconsistently and only under conditions you cannot easily reproduce.
A75: E08-S09 | B75: E08 | C75: NEWS INTELLIGENCE | D75: News UI surface | E75: New | F75: P1 | G75: 4 | H75: Low | I75: FEAT | J75: 1 | K75: E08-S08, E17-S05 | R75: 0 | V75: Show today's articles and decayed older contributions on symbol detail.
A76: E09-S01 | B76: E09 | C76: MACRO CONTEXT | D76: GIFT Nifty gap prediction | E76: New | F76: P1 | G76: 3 | H76: Correctness-critical | I76: FEAT | J76: 1 | R76: 3 | S76: As a trader, I want the expected opening gap, so that the pre-market plan accounts for where the market will actually open. | T76: 1. Fetch GIFT Nifty at ~09:00 2. Compute premium/discount vs previous Nifty close 3. Direction only — magnitude is unreliable (~85–90% direction accuracy)
A77: E09-S02 | B77: E09 | C77: MACRO CONTEXT | D77: India VIX ingestion | E77: New | F77: P1 | G77: 3 | H77: Low | I77: FEAT | J77: 0.5 | R77: 0 | V77: Current level, 30-day percentile, direction. Feeds regime and sizing.
A78: E09-S03 | B78: E09 | C78: MACRO CONTEXT | D78: FII/DII flow data | E78: New | F78: P1 | G78: 3 | H78: Low | I78: FEAT | J78: 1 | R78: 0 | V78: Daily cash and F&O net figures; rolling 3-day trend.
A79: E09-S04 | B79: E09 | C79: MACRO CONTEXT | D79: Sector rotation ranking | E79: New | F79: P1 | G79: 3 | H79: Correctness-critical | I79: FEAT | J79: 1.5 | R79: 4 | T79: 1. Fetch 24+ NSE sectoral indices 2. EOD/multi-day strength, not intraday — intraday ranks are noise 3. Relative strength vs Nifty 4. Breadth per sector
A80: E09-S05 | B80: E09 | C80: MACRO CONTEXT | D80: Economic calendar and event blackout | E80: New | F80: P1 | G80: 3 | H80: Safety-critical | I80: FEAT | J80: 1.5 | R80: 4 | S80: As a risk-aware trader, I want to stand down around scheduled volatility events, so that a technical thesis is not run over by an RBI announcement. | T80: 1. Fetch RBI policy, CPI, GDP, budget dates 2. Blackout windows from config 3. Union Budget full-day halt 4. Block new entries during blackout | U80: • 🔴 No entry is placed inside a configured blackout window | X80: Blocking new entries during a blackout is only half of it. Decide explicitly what happens to positions ALREADY OPEN when a blackout starts — hold, or exit early? An RBI announcement mid-session with open positions is the case that matters, and the tasks do not say.
A81: E09-S06 | B81: E09 | C81: MACRO CONTEXT | D81: Market regime classification | E81: New | F81: P1 | G81: 3 | H81: Correctness-critical | I81: FEAT | J81: 1.5 | K81: E09-S02, E09-S04 | R81: 4 | T81: 1. Rule-based classifier: VIX + index trend + breadth + flows 2. Output: RISK_ON / RISK_OFF / HIGH_VOL / LOW_VOL / TRENDING / RANGEBOUND 3. Hysteresis to prevent flapping 4. Log regime changes
A82: E09-S07 | B82: E09 | C82: MACRO CONTEXT | D82: MarketContext assembly with staleness | E82: New | F82: P1 | G82: 3 | H82: Safety-critical | I82: FEAT | J82: 1 | K82: E09-S01..S06 | R82: 5 | S82: As a consumer, I want every macro field to carry its own age, so that I cannot read stale data without knowing. | T82: 1. Concurrent collection with per-collector timeout 2. `FieldWithStaleness[T]` wrapper — value plus `as_of` plus `is_stale` 3. Failed collector → `None` + flag, never an exception 4. `degraded_fields` list on the context 5. Cache in Redis with TTL | U82: • 🔴 A dead collector produces a usable context with an explicit gap | X82: A usable context with an explicit gap is right, but this is won or lost at the CONSUMERS. Every read site must branch on is_stale; one that ignores the flag reintroduces exactly the silent-stale-data failure this story exists to prevent. Consider making the value inaccessible without acknowledging the flag, rather than a flag sitting beside it.
A83: E09-S08 | B83: E09 | C83: MACRO CONTEXT | D83: Intermarket signals | E83: New | F83: P2 | G83: 6 | H83: Low | I83: FEAT | J83: 1 | R83: 0 | V83: USD/INR and crude effects on sector expectations.
A84: E10-S01 | B84: E10 | C84: AI LAYER | D84: Anthropic client wrapper | E84: New | F84: P0 | G84: 3 | H84: Safety-critical | I84: FEAT | J84: 1.5 | R84: 5 | T84: 1. Async client with per-tier model selection 2. Timeout per tier from config 3. Retry with backoff on transient errors 4. Check `stop_reason` before reading `content` 5. Structured request/response logging with token counts | U84: • 🔴 A refusal never crashes the caller
A85: E10-S02 | B85: E10 | C85: AI LAYER | D85: Prompt template system with caching | E85: New | F85: P0 | G85: 3 | H85: Safety-critical | I85: FEAT | J85: 2 | K85: E10-S01 | R85: 5 | S85: As a cost-conscious operator, I want prompts structured for cache hits, so that repeated calls do not pay full price. | T85: 1. Three-layer structure: frozen system / daily context / volatile per-call 2. `cache_control` breakpoints at the right boundaries 3. Versioned templates in `ai/prompts/` 4. No timestamps, UUIDs, or unsorted dicts in the cached prefix 5. Assert prompt determinism in tests | U85: • 🔴 `cache_read_input_tokens` > 0 on the second identical-prefix call • Alert if the cache hit rate drops below threshold | X85: The cache-hit assertion needs a REAL second call, not a mock — this is precisely the class of thing that passes in tests and costs 10x in production. Also the daily-context layer changes each morning, so the cache is cold on the first call of every day BY DESIGN; set the alert threshold so it does not page you at 08:45 daily.
A86: E10-S03 | B86: E10 | C86: AI LAYER | D86: Structured output schemas | E86: New | F86: P0 | G86: 3 | H86: Safety-critical | I86: FEAT | J86: 1 | K86: E10-S01 | R86: 4 | T86: 1. `AIReview`, `DailyThesis`, `Playbook`, `NewsSignal` Pydantic models 2. `messages.parse()` integration 3. Schema validation failure → skip, log raw response 4. No `temperature`/`top_p` (rejected by current models)
A87: E10-S04 | B87: E10 | C87: AI LAYER | D87: Token budget and cost control | E87: New | F87: P0 | G87: 3 | H87: Safety-critical | I87: FEAT | J87: 1 | K87: E10-S01 | R87: 5 | T87: 1. Redis counter for daily token spend 2. Alert at `alert_at_pct` 3. Hard stop at 100% → degrade to score-only mode, keep trading 4. Per-tier cost attribution 5. Daily cost report | U87: • 🔴 Budget exhaustion degrades capability; it never halts risk management | X87: 'Degrade to score-only, keep trading' is the right direction, but verify the degraded path is actually exercised. A score-only mode that has never run will not work the first time it is needed — and the first time it is needed is mid-session with the budget already exhausted.
A88: E10-S05 | B88: E10 | C88: AI LAYER | D88: In-session AI review | E88: New | F88: P0 | G88: 4 | H88: Safety-critical | I88: FEAT | J88: 1.5 | K88: E10-S02, E10-S03 | R88: 5 | T88: 1. Render trigger + MTF snapshot + market context into the volatile layer 2. Sonnet call with `AIReview` output 3. Timeout → skip trade (fail closed) 4. Bounded concurrency via semaphore 5. Full request/response to audit log
A89: E10-S06 | B89: E10 | C89: AI LAYER | D89: Response caching for backtest | E89: New | F89: P1 | G89: 5 | H89: Correctness-critical | I89: FEAT | J89: 1.5 | K89: E10-S01 | R89: 3 | S89: As a backtester, I want historical AI outputs replayed rather than re-called, so that backtests are deterministic and free. | T89: 1. Cache keyed by prompt hash 2. Replay mode reads cache, never calls the API 3. Cache-miss policy in replay: fail loudly, do not silently call | X89: The cache key must include the MODEL ID and the prompt template version. Without them, a model upgrade silently replays old answers against new prompts and the backtest becomes fiction while still looking green.
A90: E10-S07 | B90: E10 | C90: AI LAYER | D90: Refusal handling and fallback | E90: New | F90: P1 | G90: 4 | H90: Safety-critical | I90: SEC | J90: 1 | K90: E10-S01 | R90: 3 | T90: 1. Detect `stop_reason == "refusal"` with category 2. Log and skip the trade 3. Alert if refusals cluster (may indicate a prompt problem)
A91: E10-S08 | B91: E10 | C91: AI LAYER | D91: Model tier routing and evaluation | E91: New | F91: P2 | G91: 6 | H91: Low | I91: FEAT | J91: 0.5 | R91: 0 | V91: A/B a cheaper tier for in-session review and compare decision quality.
A92: E11-S01 | B92: E11 | C92: PRE-MARKET ENGINE | D92: Pipeline orchestration with checkpointing | E92: New | F92: P0 | G92: 3 | H92: Safety-critical | I92: FEAT | J92: 2 | K92: E01-S02 | R92: 5 | S92: As an operator, I want the pre-market pipeline to resume from where it failed, so that a crash at 08:50 does not mean recomputing three hours of work with 25 minutes until the open. | T92: 1. Stage abstraction with per-stage deadline 2. Checkpoint each stage output keyed by (date, stage) 3. Resume from the last completed stage 4. Overall deadline: hard stop at 09:12 5. Alert on stage overrun | U92: • 🔴 Killing the job mid-pipeline and restarting resumes correctly • The plan is published by 09:12 or the day is flagged degraded | X92: Checkpoint-resume and the hard 09:12 deadline interact badly. A resumed run inherits the elapsed wall clock, so a job that died at 08:50 and restarts at 09:05 must know it cannot finish and publish a DEGRADED plan rather than a late one. Make the deadline absolute, not per-attempt.
A93: E11-S02 | B93: E11 | C93: PRE-MARKET ENGINE | D93: Data sync stage (05:30) | E93: New | F93: P0 | G93: 3 | H93: Correctness-critical | I93: FEAT | J93: 0.5 | K93: E03-S01, E04 (all) | R93: 0
A94: E11-S03 | B94: E11 | C94: PRE-MARKET ENGINE | D94: Universe construction stage (06:30) | E94: New | F94: P0 | G94: 3 | H94: Correctness-critical | I94: FEAT | J94: 0.5 | K94: E07-S02 | R94: 0
A95: E11-S04 | B95: E11 | C95: PRE-MARKET ENGINE | D95: Multi-timeframe analysis stage (07:30) | E95: New | F95: P0 | G95: 3 | H95: Correctness-critical | I95: FEAT | J95: 2 | K95: E06-S03 | R95: 5 | S95: As the heaviest compute of the day, this must complete in 45 minutes across the eligible universe. | T95: 1. `ProcessPoolExecutor` fan-out across symbol slices 2. Weekly/daily/hourly indicator computation from stored history 3. Serialise snapshots back to the parent 4. Progress reporting 5. Graceful degradation if a symbol's history is insufficient | U95: • 200 symbols × 3 timeframes complete in < 30 minutes | X95: ProcessPoolExecutor pickles every object crossing the boundary. Decimal and Pydantic models pickle, but at 200 symbols x 3 timeframes the serialisation cost is real and this stage owns the binding 30-minute budget of the morning. Measure the serialisation share BEFORE optimising the compute.
A96: E11-S05 | B96: E11 | C96: PRE-MARKET ENGINE | D96: News and macro sweep stage (08:15) | E96: New | F96: P0 | G96: 3 | H96: Correctness-critical | I96: FEAT | J96: 0.5 | K96: E08, E09 | R96: 0
A97: E11-S06 | B97: E11 | C97: PRE-MARKET ENGINE | D97: AI deep synthesis stage (08:45) ⭐ | E97: New | F97: P0 | G97: 3 | H97: Safety-critical | I97: FEAT | J97: 2 | K97: E10-S02, E11-S04 | R97: 7 | S97: As a trader, I want a written market thesis and per-stock playbooks before the open, so that the session is execution of a plan rather than analysis under pressure. | T97: 1. Assemble shortlist + MTF features + news + macro + journal into the prompt 2. Opus call with `DailyThesis` + `Playbook[]` structured output 3. Thesis: regime, bias, key levels, invalidation conditions 4. Playbook per candidate: setup, why, confirms, invalidates, direction 5. AI may veto or re-rank within the shortlist 6. Persist with token usage and latency 7. Deadline 09:00 → proceed score-only, mark `ai_unavailable` | U97: • 🔴 A timeout produces a valid score-only plan, not a missing plan • Every candidate's playbook is traceable to its inputs | X97: 'AI may veto or re-rank within the shortlist' is the one place the AI touches selection. Bound it explicitly: it must NOT be able to introduce a symbol that failed a hard filter, and a veto must carry a recorded reason. Re-ranking is a judgement; adding a symbol would be a safety breach.
A98: E11-S07 | B98: E11 | C98: PRE-MARKET ENGINE | D98: Pre-open gap adjustment (09:02) | E98: New | F98: P0 | G98: 3 | H98: Safety-critical | I98: FEAT | J98: 1.5 | K98: E09-S01, E11-S06 | R98: 5 | S98: As a trader, I want the plan re-ranked with actual opening prices, so that a stock that gapped past its entry is not traded on a stale thesis. | T98: 1. Read pre-open equilibrium prices 2. Compute per-stock gap vs previous close 3. Invalidate if gap exceeds `invalidate_if_gap_exceeds_pct` 4. Promote gap-and-go candidates 5. Keep invalidated candidates visible with reason | U98: • 🔴 A candidate that gapped past its entry cannot be traded on the old plan
A99: E11-S08 | B99: E11 | C99: PRE-MARKET ENGINE | D99: Plan lock and briefing delivery (09:12) | E99: New | F99: P0 | G99: 3 | H99: Safety-critical | I99: FEAT | J99: 1 | K99: E11-S07, E19-S02 | R99: 5 | T99: 1. Freeze the plan — immutable for the session 2. Record config hash with the plan 3. Persist to DB and Redis 4. Verify broker auth, margin, connectivity 5. Deliver briefing to Telegram by 09:13 | U99: • 🔴 The plan cannot be modified after lock • Briefing arrives before 09:15 on 20 consecutive sessions | X99: 'Immutable for the session' needs enforcement, not convention. E11-S07 runs at 09:02 and lock is at 09:12 — verify nothing in between can write after the lock, including a late-returning async task from an earlier stage that completes after its deadline.
A100: E12-S01 | B100: E12 | C100: STRATEGY ENGINE | D100: Strategy registry and persistence | E100: New | F100: P0 | G100: 5 | H100: Correctness-critical | I100: FEAT | J100: 1.5 | K100: E01-S01 | R100: 4 | T100: 1. Persist `StrategyDocument` to the `strategy` table 2. Load and compile on startup 3. Version and lineage tracking 4. Content-hash deduplication
A101: E12-S02 | B101: E12 | C101: STRATEGY ENGINE | D101: Lifecycle state machine | E101: New | F101: P0 | G101: 5 | H101: Safety-critical | I101: FEAT | J101: 1.5 | K101: E12-S01 | R101: 5 | T101: 1. Implement the state machine from STRATEGY_ENGINE §4 2. Gate conditions per transition 3. Human approval required for ACTIVE — not overridable 4. State change audit trail 5. Illegal transitions rejected | U101: • 🔴 No code path promotes a strategy to ACTIVE without a recorded human approval
...

Sheet Blockers
A1: CROSS-CUTTING BLOCKERS
A2: These gate multiple epics and are not code. Resolve first.
A4: ID | B4: Blocker | C4: Blocks | D4: Action Required | E4: Status | F4: Owner | G4: Target Date | H4: Resolution Notes
A5: B1 | B5: Algo-ID attachment mechanic unconfirmed | C5: Nothing. E21-S01 cancelled; E02-S04 unblocked | D5: NONE. The question was malformed: it asked HOW an Algo-ID is attached, and the answer is that at this system's operating profile there is none to attach. No email to Zerodha was needed or sent. | E5: CLOSED 9 Sep 2026 - NOT APPLICABLE | F5: Self | H5: CLOSED 9 Sep 2026 by primary-source research, superseding the Aug 2026 narrowing that called this 'a one-line email'. THE FINDING: below SEBI's 10 orders/sec threshold a self-developed personal algo is NOT REGISTERED, so no Algo-ID is issued and there is nothing for the developer to obtain or attach - the order is tagged with a GENERIC identifier on the broker/exchange side. EVIDENCE, four independent lines: (1) SEBI/HO/MIRSD/MIRSD-PoD/P/CIR/2025/0000013 of 4 Feb 2025, clause I(c) - self-developed retail algos register 'only if they cross the specified order per second threshold'; clause I(d) - brokers categorise as algo orders those 'above the specified threshold'. (2) The apparent counter-clause II(b) ('all algo orders shall be tagged') sits under STOCK BROKER responsibilities, and I(b) scopes developer-side tagging to APIs 'extended by brokers to algo providers' - a personal algo is not an algo provider. (3) Zerodha's own Z-Connect summary of the NSE circular: orders 'tagged with generic ID (unregistered, <=10 OPS)', and the only thing asked of the developer is a static IP dedicated to the API key. (4) The installed SDK: kiteconnect 5.2.1 documents place_order's algo_id as 'an optional algo ID to associate with the order', default None. RESIDUAL UNCERTAINTY, recorded honestly: NSE's FAQ of 3 Nov 2025 could not be fetched directly - NSE refuses non-Indian IPs, which is blocker B8. The NSE line is therefore via Zerodha's summary and secondary reporting rather than the source PDF. Zerodha's statement governs this account and is unambiguous. Re-read the FAQ from the VPS once B6 is done. WHAT THIS CHANGED IN THE CODE, and it is the part that mattered: common/config.py refused to load in LIVE mode without broker.algo_id. That gate failed CLOSED, so it was safe - but it would have blocked go-live PERMANENTLY on paperwork that is never issued. It is now conditional on execution.max_orders_per_second >= SEBI_ALGO_REGISTRATION_OPS (10), with a module-level guard that refuses to import if MAX_ORDERS_PER_SECOND is ever raised to meet it - crossing that line is a change of REGULATORY REGIME, not of throughput. doctor.py now reports an unset algo_id as OK rather than as an outstanding task. WHAT DID NOT DISSOLVE: the static IP (B6). Mandatory at every order rate; orders from an unwhitelisted address are rejected outright. That is now the only outstanding SEBI item.
A6: B2 | B6: pykiteconnect lacks market_protection | C6: E02-S04, E15-S01 | D6: Install from git main, or wait for release | E6: Closed | F6: Self | H6: RESOLVED 7 Aug 2026 — the wait is over; no action needed. VERIFIED ON THE INSTALLED SDK: kiteconnect 5.2.1 (current on PyPI) DOES expose market_protection on KiteConnect.place_order(). The gap was in 5.1.0, which is what the design documents were written against. Confirmed by inspecting the live signature, and by its own docstring: "market_protection accepts -1 for automatic market protection applied by the system as per market protection guidelines, or a value greater than 0 up to 100 representing a percentage." That matches EXACTLY what OrderRequest's validator already enforces (common/models/trading.py): -1 or a positive percentage, 0 rejected. The model and the broker agree without any change being needed. scripts/doctor.py verifies this at runtime and now reports the version correctly (it previously printed a module object, because `kiteconnect.__version__` is a submodule not a string — fixed). ACTION: pin `kiteconnect>=5.2.1` in pyproject so a downgrade cannot silently reintroduce the gap. [YOUR ORIGINAL NOTE: "I would prefer 'wait for release'."] — the release had already landed.
A7: B3 | B7: NSE holiday list incomplete | C7: E04-S07, all scheduling | D7: Full 2026 NSE holiday list transcribed and cross-checked against THREE independent publications of the circular, because the first two disagreed: one omitted 24 Nov (Guru Nanak Jayanti), the other omitted 15 Jan (Maharashtra municipal elections - a separate special closure rather than part of the annual circular). Both are real; both are included. 19 dates, verified_against_nse_circular: true, yielding 245 trading days in 2026. Muhurat trading (Sun 8 Nov) recorded as a special session with trade: false - it is a real session on a SUNDAY, so anything reasoning 'weekend implies closed' is wrong on that date. Also added: the calendar now REFUSES to answer for a year the file does not cover, because a 2026-only list would make 2027 look like a year with no holidays at all. | E7: RESOLVED 24 Aug 2026 | F7: Self | H7: SPRINT 1 — DAY 2. Independent desk work, no external dependency, so it pairs well with the schema day. config/nse_holidays.yaml currently carries fixed-date holidays only (Republic Day, Maharashtra Day, Gandhi Jayanti, Christmas, Good Friday 2026-04-03) and is flagged verified_against_nse_circular: false. Transcribe the full NSE circular for the trading year, including the lunar-calendar holidays that cannot be computed, then set the flag true. scripts/doctor.py already warns via check_market_calendar() when the list is incomplete, so the gap is not silent — but every scheduling decision in the system reads this file, which is why it blocks broadly. [YOUR ORIGINAL NOTE: "Research on this topic, and arrive at a relevant answer"]
A8: B4 | B8: Historical data pricing unconfirmed | C8: E03-S03 budget | D8: Ask Zerodha | E8: Closed | F8: Self | H8: RESOLVED Aug 2026 by checking Zerodha's own pricing page rather than the working assumption. Kite Connect was restructured. The Personal tier is FREE - order management, GTT, alerts, margins, portfolio - but carries NO data at all, so it cannot feed this system. Connect at Rs.500/month per app adds real-time data over WebSocket AND historical candle data. There is no separate historical add-on any more. Total cost for what this system needs is Rs.500/month, not the Rs.500 + Rs.2000 the design documents assumed. broker/profiles.py updated: historical_data_extra_cost is now False. ACTION: subscribe. It is the cheapest item on the critical path and it unblocks E03-S03 and all of E05.
A9: B5 | B9: Daily login mechanism untested | C9: E02-S01 | D9: Unchanged and genuinely blocked on you: the daily re-auth flow cannot be exercised without a real Kite account. The code path is built and unit-tested against a fake client; what is untested is the live phone-to-callback round trip. | E9: Active - needs your credentials | F9: Self | H9: NOT SPRINT 1 — needs E02 to exist before there is anything to prototype against. Scheduled to surface in Sprint 3 (E02-S01..S03). Constraint is already accepted: Zerodha requires a browser redirect with daily token expiry, so one manual human login per trading morning before the pre-open is a permanent floor, not a temporary gap. The prototype work is the phone -> callback capture flow, not an attempt to remove the touchpoint.
A10: B6 | B10: Static IP not procured | C10: E23-S02, all live trading | D10: Confirmed from Zerodha's own developer forum: the static IP applies to ORDER ENDPOINTS ONLY. WebSocket market data, order book, positions and every other endpoint remain accessible from any IP - so E03/E04/E05/E06 and all strategy work need no static IP. Registration is live at developers.kite.trade under 'IP Whitelist'; ONE IP per app; orders from an unregistered IP are rejected outright. Also confirmed there: 10 OPS is account-wide across all apps for a client ID (we cap at 5), market protection of 0 is rejected including for SL-M, and order slicing is capped at 10 slices. Only the procurement itself needs you. | E10: Active - research complete, procurement needs you | F10: Self | H10: SPRINT 1 — PROCEDURE NOW DOCUMENTED in EPIC01_TECHNICAL_SPEC.md §17.1. Not a coding task, but it gates ALL live trading, so start it early — procurement has lead time. 1. Choose the host: an Indian VPS with a dedicated IPv4 included (simplest/cheapest), or AWS ap-south-1 EC2 with an Elastic IP, or any provider offering a static/reserved IP in an India region. SEBI requires only that it is static AND India-hosted. 2. Provision, then confirm the actual EGRESS IP from the box itself with curl -s https://api.ipify.org — the assigned IP and the egress IP can differ behind NAT, and the egress value is what the broker sees. 3. Whitelist it: developers.kite.trade -> your app's profile page -> IP Whitelist. IPv4 and IPv6 both accepted. 4. Record it: system.static_ip in system.yaml and EXPECTED_EGRESS_IP in .env. 5. Verify BOTH directions: make doctor compares live egress against config and fails on mismatch; then test the negative case — an order attempt from a non-whitelisted address must be REJECTED. Only the negative test proves the whitelist is actually enforcing. Two things to know before picking a provider: the static IP applies to ORDER ENDPOINTS ONLY (quotes, WebSocket and positions work from any IP, so a data-only fallback needs no whitelisted address); and each IP binds to ONE Zerodha account. [YOUR ORIGINAL NOTE: "Explain on the procedure for this"] CONFIRMED Aug 2026 from Zerodha: all order requests from an unregistered IP will be rejected. Whitelist at the developer console, Profile, IP Whitelist; up to two IPs (one primary mandatory, one optional secondary); shareable only with immediate family. IMPORTANT AND USEFUL: validation applies to ORDER endpoints only. Quotes, historical data and the WebSocket work from anywhere - so ALL of E03, E04, E05 and E06 can be built and tested before the VPS exists. Only order placement is gated.
A11: B7 | B11: kiteconnect pins a vulnerable autobahn (CVE-2020-35678) | C11: E02-S03 WebSocket ticker, all live market data | D11: CLOSED. No environment we build contains the vulnerable autobahn, and CI asserts that from inside its own runner rather than being told so. HOW, and this is the part the first attempt got wrong: a floor of autobahn>=20.12.3 in pyproject.toml is UNSATISFIABLE. kiteconnect's ==19.11.2 is a hard pin, so pip fails with ResolutionImpossible rather than warning, and every CI job broke for two commits. It passed locally only because the package had been force-installed over an already-resolved environment - the environment being verified was one that pip install could never produce. The pin is DECLARATIVE, not a runtime requirement, so resolution runs first and the package is then replaced: pip install -c constraints.txt -e ".[dev]" pip install --no-deps --upgrade "autobahn==26.7.1" applied in all three CI install jobs, ops/Dockerfile and `make install`. EVIDENCE: tests/security/test_dependency_hygiene.py runs inside CI's Security job (pytest tests/security/) and asserts, without skipping, that the INSTALLED autobahn is >= 20.12.3, that kiteconnect still imports under it, and that market_protection and algo_id survive on place_order. DEV 0acab9b and QA 24ae953 are green on all five jobs. pip-audit reports zero known vulnerabilities and is a hard gate. | E11: CLOSED 24 Aug 2026 - verified in CI | F11: Self | G11: None | H11: RE-SCOPED Aug 2026 - there is a real way out, and it removes a second problem at the same time. kiteconnect 5.2.1 (July 2026, the latest) STILL pins autobahn[twisted]==19.11.2. Upstream has not fixed it and will not on our schedule. BUT the Kite WebSocket protocol is fully documented - endpoint wss://ws.kite.trade, JSON subscribe messages, and byte-level packet layouts for ltp (8B), quote (44B) and full (184B). So E05-S01 can be built on the websockets library instead of KiteTicker. That makes the vulnerable autobahn code UNREACHABLE (never imported) and simultaneously removes the Twisted-to-asyncio bridging problem E05-S01 was carrying. Honest caveat: autobahn stays INSTALLED, because kiteconnect hard-depends on it, so pip-audit will keep flagging it. The defensible position is installed-but-unreachable, provable with a test asserting autobahn is not in sys.modules after importing the app. KiteMarketDataAdapter.subscribe() already raises NotImplementedError naming this decision, so nobody wires up the vulnerable path by reflex.
A12: CA-B1 | B12: `ohlcv.is_adjusted BOOLEAN` cannot support re-adjustment | C12: E03-S02, E06 (all indicators), E22 (backtest validity) | D12: Redesign the adjustment storage model before any price is adjusted | E12: Closed | F12: Self | H12: RESOLVED 11 Aug 2026 — schema redesigned, built and tested. Full analysis in SPRINT02_TECHNICAL_SPEC.md §4. WHY IT WAS BLOCKING: a boolean records THAT a bar was adjusted, not BY HOW MUCH. The second corporate action therefore has nothing to build on, and adjusting the stored price in place compounds the first adjustment with no error and no failing test. Safety-critical: a wrong adjustment is silent, and it invalidates every backtest over that symbol rather than throwing. RESOLUTION: raw OHLC is immutable (BR-15). `corporate_action` holds the actions (BR-19); each bar carries `price_adj_factor` and `volume_adj_factor`; the repository applies them on read. Recompute rebuilds from the full history, so it is idempotent and a bad action is fixed by correcting the row. NOT A BLOCKER ANYMORE, but E03-S02 stays open: the adjustment ENGINE is done, the corporate action FEED is not, and that needs a data source — which is the same credential dependency as B1/B4, not a design gap.
A13: B8 | B13: NSE blocks programmatic access to its public data | C13: E04 (all 7 stories), E03-S01, E03-S02 feed | D13: What NSE blocks is OVERSEAS access, not programmatic access as such: its edge refuses non-Indian IPs and its robots policy excludes crawlers, but a polite client on an Indian host carrying the session cookie its own site issues is an ordinary visitor. Community libraries (nsepython, NseIndiaApi at 3 req/s) work on Indian servers. This collapses B8 into B6: SEBI already requires an India-hosted static IP for the order path, and the same host answers the data question. Built scripts/check_data_reachability.py so the answer is one command on the day there is a host - read-only, no credentials, safe during market hours. Run from THIS machine it already reaches 4 of 6 sources including Kite instruments and NSE marketStatus. | E13: Narrowed - same fix as B6 | F13: Self | H13: FOUND Aug 2026 during next-steps research. NSE actively blocks scripted access to its website, and in 2025 NSE and BSE restricted website access for overseas users entirely. SCOPE - this affects DAILY REFERENCE DATA, not live market data. Live ticks and historical candles come from Kite Connect, an authenticated commercial API, and are completely unaffected. What is affected is the 05:30 fetch of ASM/GSM, T2T, F&O ban, circuit bands, CAS scope, the earnings calendar, bhavcopy and corporate actions - all of which come from NSE's public site. It is a fetch-RELIABILITY problem, not a wall. The data is public; the difficulty is that the site is hostile to automation and changes shape without notice. Kite's instrument dump does NOT help - it carries token, symbol, tick size, lot size and segment, with no series, ASM, GSM, T2T or ban field (verified against the API docs). MITIGATIONS: jugaad-data (actively maintained, with caching specifically to avoid being blocked); nsefin for corporate actions, which is also E03-S02's missing feed; BSE as a fallback since ~90% of NSE equities are dual-listed; Zerodha's consolidated scrip sheet as a cross-check only (no SLA). The India-hosted VPS already required by constraint C1 sidesteps the geo-restriction. WHY IT IS SURVIVABLE: the fetch runs at 05:30, hours before the open, so a failure has a long runway for a retry, a fallback source or a manual override. E04-S01's acceptance criterion already says a fetch failure blocks the trading day rather than proceeding blind - the right posture: a bad fetch costs a trading day, not money. ACTION: spend an hour proving NSE reachability from the target environment before writing fetchers. That assumption sits under 8 stories and roughly 10 days of work.
A14: B9 | B14: kiteconnect runs against an autobahn it does not declare support for | C14: Nothing today. A future kiteconnect release could. | D14: Registered as its own row rather than folded into B7, because it is a different risk with a different resolution. B7 was 'a vulnerable package is present'. This is 'we run an undeclared combination'. `pip check` reports it plainly: kiteconnect 5.2.1 has requirement autobahn[twisted]==19.11.2, but you have autobahn 26.7.1. Two consequences: 1. Only kiteconnect.ticker imports autobahn, and we never construct a KiteTicker - the live feed is built on `websockets` against the documented binary protocol. So nothing we call depends on the pinned API. 2. --no-deps means autobahn 26.7.1's own dependencies are not pulled by that step. They are satisfied in practice - CI imports kiteconnect successfully, which transitively imports autobahn.twisted.websocket - but that is an observed property of the environment rather than a declared one. WATCHED BY: test_kiteconnect_still_imports_under_the_replacement and test_the_order_parameters_we_depend_on_survive. If a future kiteconnect genuinely needs 19.11.2's API, those fail rather than an order being rejected at the exchange. RESOLVES PERMANENTLY when kiteconnect relaxes its pin, or when the REST client is replaced - we use it for KiteConnect and kiteconnect.exceptions only, and it is a thin requests wrapper. Not worth doing for this reason alone. | E14: Accepted risk - watched by tests | F14: Self | H14: Opened 24 Aug 2026, as the residual of closing B7. Reviewed whenever kiteconnect is upgraded.

Sheet E01 Blockers
A1: E01 BLOCKERS — PERSISTENCE & DATA LAYER
A2: Blockers specific to E01 items. A blocker is something that cannot be resolved from inside the project and that prevents CORRECT completion — not 'this is hard'. See DEVELOPMENT_PROCEDURE.md §8.
A4: ID | B4: Blocker | C4: Blocks | D4: Action Required | E4: Status | F4: Owner | G4: Target Date | H4: Resolution Notes
A5: E01-B1 | B5: None identified — every remaining E01 item is buildable | C5: nothing | D5: No action. Recorded so the absence is explicit rather than assumed. | E5: Closed | F5: Self | G5: None | H5: Assessed 7 Aug 2026 before starting E01-S02/S03/S04/S05/S06. E01 depends on NO external credential, account or third-party answer. Postgres and Redis are local containers; nothing in the epic touches the broker, the AI provider, news, or the static IP. The blockers that DO exist (B1 Algo-ID value, B4 data pricing, B6 static IP, B7 autobahn CVE) all gate E02+ or live trading, NOT E01. Verified against the main Blockers sheet. The one thing that LOOKED like an E01 blocker — the undecided TimescaleDB pin — was DESIGNED AWAY rather than waited on: the migration detects the installed version at runtime and emits matching DDL, verified on 2.17.2 and 2.29.1. That is the preferred resolution when one exists (DEVELOPMENT_PROCEDURE.md §8.2).

Sheet QA Results
A1: QA RESULTS — E01 END-TO-END
A2: End-to-end verification of the persistence layer as ONE system. Per-story suites test components in isolation; these test the SEAMS between them, which is where integration defects live. Run: pytest tests/integration/ (requires Docker).
A4: QA ID | B4: Story | C4: Area | D4: Result | E4: What was verified | F4: Evidence | G4: Test file | I4: Result | J4: Count
A5: QA-E01-01 | B5: E01-S01 | C5: Instrument sync | D5: PASS | E5: Upsert is idempotent; symbol<->id cache resolves; a new listing mid-session needs no restart | F5: 50 lookups issue 0 queries | G5: test_e01_end_to_end.py | I5: PASS | J5: 30
A6: QA-E01-02 | B6: E01-S01 | C6: Hazard flags + eligibility view | D6: PASS | E6: Per-symbol-per-day flags stored; v_eligible_today excludes T2T/ASM/GSM and is IST-anchored | F6: T2T symbol correctly excluded | G6: test_schema_business_rules.py | I6: FAIL -> FIXED | J6: 11
A7: QA-E01-03 | B7: E01-S02 | C7: Bar write and warm-up read | D7: PASS | E7: 30 bars written; warm_up_batch returns them oldest-first as exact Decimals | F7: query count constant vs symbol count | G7: test_repositories.py | I7: BLOCKED | J7: 0
A8: QA-E01-04 | B8: E01-S03 | C8: Redis typed state round trip | D8: PASS | E8: Decimal survives model_dump_json exactly; corrupt payload reads as absent | F8: 1510.7500 in == 1510.7500 out | G8: test_redis_layer.py
A9: QA-E01-05 | B9: E01-S03 | C9: Slot lock + DB unique index | D9: PASS | E9: Lock refuses the second holder; partial unique index refuses the second insert independently | F9: both layers hold | G9: test_e01_end_to_end.py
A10: QA-E01-06 | B10: E01-S04 | C10: Signal across the stream | D10: PASS | E10: Envelope published and consumed; correlation_id preserved end to end | F10: correlation_id matches | G10: test_event_streams.py
A11: QA-E01-07 | B11: E01-S03 | C11: Order rate limiting | D11: PASS | E11: Token bucket gates before submission; 25 concurrent callers yield exactly capacity | F11: exactly 5 of 25 allowed | G11: test_redis_layer.py
A12: QA-E01-08 | B12: E01-S02 | C12: Two-transaction order submission | D12: PASS | E12: SUBMITTING row exists before the broker call; recovery finds it by client_order_id | F12: status transitions correctly | G12: test_e01_end_to_end.py
A13: QA-E01-09 | B13: E01-S01 | C13: Position with stop + deadline | D13: PASS | E13: BR-1 and BR-7 enforced NOT NULL; slot occupied then freed on close | F13: naked position impossible | G13: test_schema_business_rules.py
A14: QA-E01-10 | B14: E01-S03 | C14: Square-off timer armed | D14: PASS | E14: ZSET schedule; pop_due is atomic across 6 concurrent workers, no double-pop | F14: 20 popped, 0 duplicates | G14: test_redis_layer.py
A15: QA-E01-11 | B15: E01-S05 | C15: Audit trail reconstructs the trade | D15: PASS | E15: 5 stages written; chain verifies; by_correlation returns them in order | F15: PREMARKET->SIGNAL->RISK->ORDER->FILL | G15: test_e01_end_to_end.py
A16: QA-E01-12 | B16: E01-S06 | C16: Archive / purge / restore cycle | D16: PASS | E16: 30 bars archived and verified, purged only after verification, restored with exact prices | F16: prices identical after restore | G16: test_retention.py
A17: QA-E01-13 | B17: cross | C17: Symbol validity agreement | D17: PASS | E17: Every symbol the instruments table accepts is also a legal Redis key | F17: M&M, BAJAJ-AUTO, L&TFH all pass | G17: test_e01_end_to_end.py
A18: QA-E01-14 | B18: cross | C18: Audit payload JSONB round trip | D18: PASS | E18: Unicode, nesting, nulls, bools and 2^53+1 all survive; chain still verifies | F18: verification clean on tricky payload | G18: test_e01_end_to_end.py
A19: QA-E01-15 | B19: cross | C19: Fail-closed on every degradation | D19: PASS | E19: Missing bars -> empty; corrupt state -> absent; Redis down -> kill switch ENGAGED; audit down -> buffered | F19: no path fails open | G19: test_e01_end_to_end.py
... A150: QA-VER-02 | B150: Process | C150: Accuracy review of the /sdlc skill against the repository, CI and the tracker, 28 Oct 2026. | D150: FAIL -> Fixed | E150: Every command, path and claim in .claude/skills/sdlc/SKILL.md checked against the repo. Inaccurate and corrected: (1) Rule 1 cited a PROD gate the promotion tool never runs (AUDIT-023); (2) `make audit`/`make test-safety`/`make doctor` - make is not installed on the development machine; direct commands given; (3) R2 'dependencies are Closed' - only E00/E01 are Closed and every E14/E15 story rightly started on QA-Success dependencies; R2 now QA-Success-or-Closed, with a status lifecycle table the skill never had; (4) promote.py strips Documents, scripts/tracker AND .claude, not Documents only; (5) the commit template hard-coded 'Claude Opus 5'; (6) the doctor gate exits 1 on any dev machine (no deployment secrets) so 'every gate green' could never pass - the expected vs blocking sections are now stated; (7) Phase 0's 'unpromoted work' query lists docs-only commits forever; the promote.py dry run is now the check; (8) the tracker artifact URL belongs to an earlier account and has been unreachable since 15 Oct 2026 - the refusal procedure is now written instead of a dead end; (9) 'tested in test_safety_invariants.py' - invariants 3 and 5 are tested in its neighbours. Missing and added: Docker and '0 skipped' as part of green (15 Oct: 332 skipped looked green), the constrained install, CI's exact lint scope, re-running the audit before push, reproducing CI-only failures in python:3.11-slim-bookworm (job logs need admin), the SIT worktree procedure, the caplog/-p no:logging pitfall, mutation-harness rules (byte-exact restore, nothing else running, wrong-reason survivors), the CI-only jobs (image build, gitleaks). | F150: The verified parts: the String(28) example (exactly three check names exceed it), the E14-S01 dependency correction and the NSE holiday triangulation are as stated in the tracker and config; every referenced file exists; the SIT scenario list matches tests/sit. ENGINEERING_STANDARD.md had the same stale R2, audit command and make-based gate - corrected in step, since the skill defers to it on process. | G150: Each corrected command was executed as written on 28 Oct 2026: the derived pip-audit line (7 ignored, 0 found), the SIT worktree procedure (181 passed on QA 6c04290, algotrader loaded from the worktree), promote.py refusing DEV->PROD, QA->PROD and DEV->main and passing the CI check on DEV's head, doctor (Configuration, Broker SDK, Market calendar, Strategies OK; Datastores FAIL as stated).

Sheet Security Findings
A1: SECURITY FINDINGS — E01 PENETRATION TEST
A2: Findings from attacking the code rather than reviewing it. Threat model: broker instrument data is untrusted external input; news and AI output reach audit payloads; an attacker WITH database access is IN SCOPE for the audit chain — that is why it is hash-chained, not merely append-only. Every finding has a regression test that fails if it is reintroduced.
A4: ID | B4: Severity | C4: Component | D4: Status | E4: Vulnerability | F4: Impact | G4: Fix | H4: Regression test | J4: Severity | K4: Count
A5: QA-SEC-01 | B5: HIGH | C5: Audit chain | D5: Fixed | E5: Hash collision via delimiter ambiguity. Material was '|'.join(fields) with the delimiter unescaped, so a field containing '|' shifted the boundary: stage='SIGNAL'/outcome='ALLOW|X' and stage='SIGNAL|ALLOW'/outcome='X' produced an IDENTICAL digest. | F5: Defeats tamper-evidence entirely — a record could be substituted for another without breaking the chain. Same class as CVE-2012-2459 (Merkle ambiguity). | G5: Length-prefix every field (len:value), making the encoding injective, plus an 'AUDITv2' domain-separation tag. Standard remedy for concatenation ambiguity. | H5: 5 parametrised collision probes + determinism control | J5: HIGH | K5: 6
A6: QA-SEC-05 | B6: HIGH | C6: Audit writer | D6: Fixed | E6: decision_log.symbol_id foreign key blocked the audit writer. PostgreSQL takes a shared lock on the referenced row to validate the FK, so an audit write referencing an instrument whose row is uncommitted waits for that business transaction. | F6: Defeats the reason AuditWriter uses an independent session. During the daily instrument sync — one transaction, thousands of rows — every concurrent audit write for those symbols stalls, then falls to the disk buffer at statement_timeout. The audit trail degrades because of an unrelated bulk write. | G6: Dropped the FK; kept the column. An audit log must be writable unconditionally and must outlive delisted instruments. TimescaleDB refuses to add an FK to a compressed hypertable at all, which is further evidence it never belonged. | H6: Two-session probe before and after the fix; E2E suite | J6: MEDIUM | K6: 7
A7: QA-SEC-03 | B7: MEDIUM | C7: Redis keyspace | D7: Fixed | E7: Broker-supplied symbols flowed unvalidated into Redis key names. ':' shifts key boundaries so two logical states share one slot; '*' and '?' are glob wildcards in any SCAN; '\n' and '\x00' are accepted by Redis but rejected by PostgreSQL. | F7: Silent state corruption in a component holding positions and the kill switch. None of these raise — the wrong value is simply read. | G7: Validate every key component against an allowlist. Deliberately permits & and - so real NSE tickers (M&M, BAJAJ-AUTO, L&TFH) are not broken — verified by a control test. | H7: 10 hostile inputs x 4 builders + 5 real-symbol controls | J7: LOW | K7: 2
A8: QA-SEC-02 | B8: MEDIUM | C8: Audit payload | D8: Fixed | E8: json.dumps coerces non-string keys, so {1:'a'} and {'1':'a'} serialised identically — two different payloads, one hash. {1:'a','1':'b'} emitted a duplicate JSON key. | F8: Canonicalisation defect in a structure whose only purpose is to be canonical. | G8: Reject non-string keys at any depth, at the boundary, rather than coercing them. | H8: 6 payload shapes refused + serialisation control | J8: INFO | K8: 1
A9: QA-SEC-06 | B9: LOW | C9: Input validation | D9: Fixed | E9: The key-rejection message echoed the entire rejected value, so a hostile 200 KB ticker produced 200 KB of log. | F9: Denial of service against the log pipeline, and a log-injection vector. | G9: Truncate the echo to 64 characters and report the true length instead. | H9: Asserts the message stays under 2 KB
A10: QA-SEC-04 | B10: LOW | C10: Event streams | D10: Fixed | E10: stream_dlq was not idempotent: a DLQ entry that itself failed produced stream:dlq:dlq:signals, then stream:dlq:dlq:dlq:signals. | F10: Unbounded key growth under repeated failure, and each new key escapes the MAXLEN configured for the stream it came from — which under noeviction is how Redis stops accepting writes. | G10: Strip an existing dlq: prefix so the operation is idempotent. | H10: Applied 5 times, key must remain stable
A11: QA-SEC-07 | B11: INFO | C11: Regex validation | D11: Fixed | E11: The first version of the key filter used re.compile(r'^...$').match(). In Python '$' also matches immediately BEFORE a trailing newline, so 'svc\n' passed validation. | F11: A newline reached the keyspace despite an apparently correct anchored pattern. Classic and easy to miss on review. | G11: Switched to fullmatch, which has no trailing-newline exception. | H11: Found by the pen-test suite failing on its own first run
A12: QA-SEC-08 | B12: HIGH | C12: Pre-flight gate (doctor.py) | D12: Fixed | E12: check_secrets hardcoded ANGELONE_API_KEY / CLIENT_ID / TOTP_SECRET while config sets broker.primary = zerodha. Those three variables appear NOWHERE else in the repo — not in .env.example, not in SETUP.md. | F12: The gate before real capital validated a broker this deployment never uses. In LIVE mode it would hard-FAIL on credentials nobody was told to set, while reporting nothing at all about the Kite credentials actually required. A pre-flight check that validates the wrong aircraft is worse than none, because it reports green. | G12: Moved the variable names onto BrokerProfile.credential_env_vars and made doctor derive them from broker.primary / broker.fallback. Fallback gaps degrade coverage rather than blocking trading. | H12: 4 tests incl. switching the configured broker switches what is checked, and a cross-check that every declared variable exists in .env.example
A13: QA-SEC-09 | B13: MEDIUM | C13: Pre-flight gate (doctor.py) | D13: Fixed | E13: BR-20 requires doctor to FAIL when the NSE holiday calendar is unverified. check_market_calendar only ever WARNED — including in LIVE mode. | F13: The system could go live with a fixed-date-only calendar, treating Diwali or any lunar-calendar holiday as a normal trading day: it would run the pre-market pipeline against data that never arrives and compute indicators across a phantom session. Nothing errors. | G13: Escalated to fail when mode is LIVE, kept as a warning otherwise so development stays usable. | H13: Live-mode and paper-mode branches both asserted in test_preflight_gate.py
A14: QA-SEC-10 | B14: MEDIUM | C14: Broker adapter | D14: Fixed | E14: ReadOnlyGuard — the mixin that stops a read-only adapter placing orders — had zero test coverage. broker/adapter.py measured 0%. | F14: MASTER_REFERENCE and LOW_LEVEL_ARCHITECTURE both claim that compromising any service other than execution-svc cannot place an order. That guarantee rested entirely on three raise statements that no test exercised; deleting them broke nothing. | G14: Added probes for place/modify/cancel, plus a structural test that fails if TradingAdapter gains a new mutating method the guard does not override. | H14: 6 tests in test_safety_invariants.py
A15: QA-SEC-11 | B15: HIGH | C15: Log redaction | D15: Fixed | E15: Secrets survived redaction and reached the log via TWO paths the filter never touched: (1) exc_info=True, because logging.Formatter renders record.exc_info itself long after every filter has run; (2) an exception passed as a format arg, because _scrub_value only handled str/dict/list so an Exception object fell through and the formatter called str() on it later. | F15: Violates invariant 3 and C6. engine.healthcheck logs with exc_info=True by design, and SQLAlchemy/psycopg/Alembic all put the connection URL in their exceptions - so the FIRST failed database healthcheck would write the DSN password to disk in clear text. The message path was perfectly redacted the whole time. | G15: Pre-render and scrub record.exc_text (the formatter uses it verbatim when set, and only falls back to exc_info when it is empty); scrub stack_info; render BaseException through the scrubber in _scrub_value. | H15: 6 tests: exc_info, exception-as-arg, chained cause, stack_info, an opaque registered value with no regex shape, plus a control that the host and exception type still survive
A16: QA-SEC-12 | B16: HIGH | C16: Database privileges | D16: Fixed | E16: corporate_action shipped with NO grants at all for algotrader_app, and its sequence had no USAGE. The grant migration enumerates tables BY NAME and ran long before the table existed. | F16: The entire E03-S02 adjustment path was dead behind a permission nobody had granted: InsufficientPrivilege on INSERT from the feed and on the SELECT inside recompute_factors. Every test passed because the harness connects as the table owner - the failure would have surfaced only in production. | G16: Migration b7c2f9a41d38 grants the table and its sequence, guarded so it is runnable where the role does not exist. Verified upgrade -> downgrade -> upgrade. | H16: 5 tests comparing the LIVE catalogue against Base.metadata, so any future table without grants fails immediately; plus an end-to-end write under SET ROLE algotrader_app
A17: QA-SEC-13 | B17: MEDIUM | C17: Supply chain | D17: Fixed | E17: No lockfile anywhere. pyproject declares floors (>=), so CI, the Docker build and a developer laptop each resolved dependencies independently. | F17: The image was not the artifact CI tested; builds were not reproducible; a breaking or compromised upstream release would land automatically on a system that holds broker credentials. The pinned ruff/mypy lines record this exact lesson for linters but it was never applied to runtime dependencies. | G17: constraints.txt with 116 pins, generated inside the SAME Linux image the Dockerfile builds from (a Windows freeze would omit uvloop and add Windows-only wheels). Wired into the Dockerfile and all three CI install steps. | H17: Image rebuilt and verified: runs non-root, imports cleanly, pins applied (SQLAlchemy 2.0.51). pip-audit re-run against the pinned set - no new vulnerabilities.
A18: QA-SEC-14 | B18: HIGH | C18: Rate limiter (E01-S03 primitive) | D18: Fixed | E18: The Redis token bucket took its clock from the CALLER (time.time() in Python, computed before the await) and wrote it to the bucket unconditionally. Concurrent callers stamp their own time and then arrive at Redis in a different order, so a late-arriving request REWINDS the stored timestamp and the next caller measures elapsed time from that older mark - being granted tokens no time actually produced. | F18: This is the limiter that keeps order rate under SEBI's 10/sec registration threshold. Measured: a burst of 3 with 3/sec refill let 11 of 100 concurrent callers through in 0.56s on an idle host, and 56 of 100 on a loaded one, against an honest ceiling of about 5. The control failed quietly under exactly the load it exists for, and every existing Redis test passed throughout because none of them exercised concurrency. | G18: Take the clock from Redis (redis.call('TIME')) inside the Lua instead of accepting one from the caller. One clock, read after serialisation, so neither reordering nor skew between processes can move it backwards. Post-fix: 4 of 100 allowed, which is burst plus honest refill. | H18: A 100-way concurrent flood asserting against burst + rate x elapsed (not a flat constant, because the bucket legitimately refills during the flood). The original flat assertion is what surfaced the bug.
A19: QA-SEC-15 | B19: MEDIUM | C19: Broker auth / login URL | D19: Fixed | E19: login_url() interpolated api_key into the Kite URL with no validation or encoding. A value of 'realkey&redirect_uri=https://evil.example.com' produces a perfectly VALID Kite login URL that returns the request_token to somebody else. CRLF in the same position was equally accepted. | F19: This defeats the anti-phishing design from the other side. The operator navigates from their own bookmark exactly as intended, lands on a genuine Zerodha page, and hands the request_token to an attacker who exchanges it with their own api_secret. Requires config/env write access - but config is editable through the Admin UI (E18-S02), and a mis-pasted key with a stray '&' fails the same way. | G19: Validate rather than escape: a Kite api_key is alphanumeric, so anything else is a mis-paste or an attempt to steer the flow. Encoding would quietly carry the mistake into a URL that then fails at the broker for an unrelated-looking reason. | H19: 5 hostile api_keys refused (& injection, CRLF, space, fragment, query), a real key still builds, and the error is asserted not to echo a 5000-char value into the log
A20: QA-SEC-16 | B20: MEDIUM | C20: Order logging / symbol handling | D20: Fixed | E20: A newline in an instrument symbol forged a whole log line. Observed output: 'placing BUY MARKET x1 for INFY 2026-01-01 CRITICAL kill switch disarmed (tag=...)' - a second, entirely fictional CRITICAL entry written by the order logger. | F20: Symbols come from the broker's daily dump, which is external data this system does not author. QA-SEC-03 established exactly this for Redis keys; the same untrusted value also reaches the order log line, and application logs are what an incident is reconstructed from. A forgeable log line is a real problem even though nothing crashes. | G20: OrderRequest.symbol now validated against the same allowlist as the Redis key builder - one definition of what a symbol may contain, applied wherever untrusted symbol text crosses a boundary. | H20: 6 hostile symbols refused (newline, CRLF, colon, glob, over-length, empty) plus a CONTROL that real Indian symbols still work: M&M, BAJAJ-AUTO, L&TFH, NIFTY.NS, IDEA_EQ
... A80: AUDIT-025 | B80: LOW | C80: Code/scripts/doctor.py - interpreter advice | D80: Fixed | E80: doctor.py warned on Python 3.11 with '3.12+ recommended', while CI, the runtime image and mypy all pin 3.11. | F80: Advice that would move a developer onto an interpreter nothing ships, so their tests describe a different system. | G80: OK on the shipped 3.11; a newer local interpreter warns that it tests what nothing ships. | H80: Run on 28 Oct 2026: Environment section reports OK on 3.11.9.

Sheet SIT Defects
A1: SIT DEFECTS — System Integration Testing
A2: Raised during SIT on the QA branch, after component and integration QA have passed. A defect here is by definition something no component test could see — record what the SYSTEM did, not what a unit returned.
A4: SIT ID | B4: Date | C4: Story | D4: Severity | E4: Component | F4: Status | G4: What happened | H4: Why component tests missed it | I4: Root cause | J4: Fix | K4: Regression test | L4: Backlog item raised
A5: SIT-001 | B5: 2026-09-02 | C5: E14-S02 | D5: MEDIUM | E5: execution/risk/framework.py | F5: Fixed | G5: Walking a full simulated session minute by minute, EVERY tradable minute came back rejected with HEALTH_GATE_FAILED — 340 of them — while every service was healthy. The four pre-condition gates had passed; the reject came from the frame underneath them. | H5: RejectReason has no member meaning 'the engine itself is broken', so the framework borrowed HEALTH_GATE_FAILED for three structurally different conditions: a check that raised, a missing sizer, and a sizer that raised. Every component test asserted the DECISION (refused — correct in all three cases) and read the reason only where it was already expected, or asserted the detail string instead. Nothing compared a genuine health-gate rejection against an engine fault side by side, and in isolation each reads perfectly sensibly. It took a whole-session run, where the same label appeared for 340 minutes with nothing unhealthy, for the overload to be visible at all. | I5: A missing enum member, filled by the nearest plausible neighbour. signals_rejected_total{reason} is described in RejectReason's own docstring as 'the highest-value debugging metric in the system, because it turns why isn't it trading? into a glance instead of an investigation'. The overload defeats exactly that: an operator glancing at a no-trade day would go looking for a downed service that is perfectly healthy. The realistic trigger is not exotic — the holiday list must be renewed each December, and a lapsed one makes the calendar raise, which is an engine fault reported as a sick service in the first week of January. | J5: Added RejectReason.RISK_ENGINE_FAULT and used it at the three framework sites. HEALTH_GATE_FAILED now means only what its name says. Every other member means 'the system worked and the answer is no'; this one means 'the system is broken and refusing is the safe reading of that'. Recorded in the framework docstring so the distinction survives the next edit. | K5: tests/sit/test_e14_trading_session.py test_an_engine_fault_is_not_reported_as_a_downed_service (compares the two side by side); test_risk_preconditions.py test_a_lapsed_holiday_list_reads_as_a_fault_not_a_sick_service; test_risk_framework.py test_a_raising_check_is_not_reported_as_a_business_rejection. Mutations M14-M16 flip each site back and are all killed. | L5: None — fixed in the same session
A6: SIT-002 | B6: 2026-09-10 | C6: E15-S02 | D6: LOW | E6: tests/sit/test_e14_trading_session.py (harness) | F6: Fixed | G6: SIT-15's replay scenario - run the day, restart, run it again against the same store - asserted that the second pass reaches the broker zero times. It failed: the second pass submitted all 316 orders again. The SYSTEM was correct; the scenario was not replaying a day, it was trading a new one. | H6: No component test can catch it. `_recommendation()` mints a fresh correlation_id on every call, and correlation_id is the first component of the idempotency key. A single-order test builds one recommendation and reuses the object, so the trap is invisible; only a scenario that rebuilds the day's signals per run steps on it. THE PROCESS FINDING, and the reason this is logged rather than quietly fixed: this is the SECOND time the same trap has fired - SIT-14's replay test hit it on 8 Sep 2026 and was corrected in place, in the caller. Fixing the caller left the helper just as sharp for the next one. | I6: A test helper whose default behaviour (fresh identity per call) is correct for most callers and silently wrong for replay scenarios, with nothing at the helper saying so. | J6: SIT-15 mints the day's signals ONCE via a `_signals(session)` helper and passes the list to both runs. The docstring on `_signals` states the trap and names SIT-14 as the prior occurrence, so the warning now lives where the next caller will read it rather than in the test that happened to trip over it. | K6: tests/sit/test_e14_trading_session.py::TestSit15ASessionThatSurvivesATimeout::test_replaying_the_whole_day_sends_nothing_the_second_time - now genuinely asserts idempotency across a restart, and fails if the duplicate check is removed (mutation M12, killed). | L6: None - fixed in the same session
A7: SIT-003 | B7: 2026-09-11 | C7: E15-S04 | D7: HIGH | E7: execution/gateway.py, common/db/repositories.py | F7: Fixed | G7: SIT-17 ran a whole session in which the broker refused every protective stop. Every position was exited correctly, every exception was the right one, and no test failed. The store finished the day holding 316 rows with status SUBMITTING - 'this order is in flight' - for orders the broker had definitively REJECTED. The broker's reason code went into an exception message and nowhere durable, past an orders.rejection_reason column that has existed since the first migration and that nothing has ever written. | H7: BECAUSE THE DEFECT IS IN WHAT THE DAY LEAVES BEHIND, NOT IN WHAT IT DOES. Every observable action was correct, so a test that asserts behaviour sees nothing wrong. There WAS a unit test for this exact input - test_an_outright_rejection_is_not_treated_as_ambiguous - and it asserted 'placer.find_calls == []': what must NOT happen. It never asked what DID happen to the row. That is the general shape: a test written to pin down a negative leaves the positive unobserved, and the state left behind is invisible until something later reads it. SIT reads it, because SIT is the only tier that runs a whole day and then looks at the record. | I7: TX1 writes SUBMITTING before place_order, and submit() caught only AmbiguousOrderError. OrderRejectedError propagated with the row untouched. The consequence is not confined to a stale row: open_orders() is documented as 'the reconciliation working set', selecting everything not in (FILLED, CANCELLED, REJECTED) - so a refused order sits in that set for the rest of the day and reconciliation (S8.3, E15-S09) would query a broker that has never heard of it, every 30 seconds, forever. Underneath: OrderStatus models REJECTED and SUBMIT_FAILED, order_state.py gives both legal edges, and NO code path in src/ ever wrote either. The state machine had states that could be read and never reached - the same shape as the exposure caps that were configured and bound nothing. | J7: submit() now catches OrderRejectedError, calls _reject(), and re-raises. _reject writes status=REJECTED plus the sanitised reason via a new OrderStore.mark_rejected, and NEVER raises: a persistence failure must not replace the broker's rejection with 'the database is down', and the row it leaves in SUBMITTING is exactly the prior behaviour. Deliberately NOT except Exception: SUBMITTING means 'we do not know whether it landed', which is the truth for an unmodelled error and the reason S8.2's query path exists. Only a documented refusal is a known outcome. No migration - the column was already there. A retry now meets a terminal REJECTED row and is refused by the state machine (IllegalTransitionError) rather than reported as OrderNeverLandedError, which had been saying 'it never landed' about an order that landed and was refused. | K7: tests/unit/test_gateway.py::TestARefusedOrderIsRecordedAsRefused (6, including two controls: an unmodelled failure still leaves SUBMITTING, and the ordinary path records no rejection); tests/integration/test_repositories.py::test_a_refused_order_is_recorded_with_the_brokers_reason and ::test_a_refused_order_leaves_the_reconciliation_working_set (real Postgres); tests/sit/...::test_a_day_of_refused_stops_leaves_no_row_claiming_to_be_in_flight. Mutation: 9 injected, 9 killed. | L7: None - fixed in the same session
A8: SIT-004 | B8: 2026-09-22 | C8: E15-S05 | D8: MEDIUM | E8: execution/positions.py | F8: Fixed | G8: Replaying a day's fills after a restart - 40 positions opened, the book restored from rows, then the same 40 fills presented again, which is exactly what happens because the broker keeps reporting yesterday's entries as FILLED. No second position was created and no second stop was placed, so the system was SAFE. But all 40 replays surfaced as a raw unique-index violation escaping open_from_fill: the caller is told the insert failed, with no way to tell 'this is already open and protected' from 'opening this failed'. | H8: The unit store is a dictionary that accepts every insert, and the integration tests each open one position. Neither shape can produce a replay: it needs the SAME fills presented twice to a store that carries state across both passes, which is a session-scale setup. The defect also hides behind a correct outcome - nothing duplicates, because the partial unique index refuses it - so only the TYPE of the failure is wrong, and only a test that asserts on the failure type would see it. The first version of this SIT test asserted merely that the replay failed, and passed. | I8: Only layer 2 of EPIC01 8.4's three-layer pattern existed for positions. The gateway applies all three to ORDERS (cheap check, uq_client_order, reconciliation) and E15-S05 inherited none of it for POSITIONS: there was no cheap check before the insert, so the database constraint was doing work it is meant to back up rather than perform. PositionRepository.open_position even documents this - 'a normal, expected outcome under concurrency, not an error to surface; callers must catch it and treat it as slot taken' - and the new caller did not. The instruction was in the docstring of the function being called, which is the easiest kind of instruction to not read. | J8: open_from_fill now checks the in-memory book first and raises PositionAlreadyHeldError, a typed, actionable answer. Deliberately AFTER confirm_fill, because 'nothing filled' is the more specific truth. The cheap check is only as good as the book - empty until restore() runs - so the partial unique indexes remain the guarantee rather than the optimisation, and E15-S09's reconciliation is the third layer behind both. | K8: tests/sit/test_e14_trading_session.py::TestSit18...::test_replaying_the_days_fills_after_a_restart (asserts the failure TYPE, not merely that it failed) plus tests/unit/test_positions.py::TestReplayingAFill (4 tests, including the control that a different symbol still opens). Mutations M25 and M26 killed. | L8: None - fixed in the same session
A9: SIT-005 | B9: 2026-09-24 | C9: E15-S09 | D9: MEDIUM | E9: execution/reconciliation.py | F9: Fixed | G9: One stranger's position on the account, seen by 30 consecutive cycles, produced 30 UNKNOWN_POS audit rows, 30 CRITICAL 'UNKNOWN POSITION' log lines and unknown_positions_total = 30. The counter's own help text says it counts positions; it was counting cycles. | H9: Every unit test of the unknown path runs ONE cycle. Repetition is a property of a session - the stranger's position stays at the broker, so every later cycle sees it again - and only a test that runs the loop after every fill of a day can see what the alert does on the thirtieth look. | I9: Detection and alerting were the same step. Refusals and duplicates had already been made report-once in this story; the unknown path - the one that matters most - had not, and the asymmetry went unnoticed until a session exercised it. | J9: Detection still runs every cycle (report.unknown). The alert - log, counter, audit row - runs when a stranger is new or its size changes. The HALT is re-armed every cycle regardless, so an operator who clears the latch while an unknown position remains is halted again by the next cycle. | K9: tests/sit/...::TestSit19...::test_a_stranger_is_alerted_once_not_every_cycle; tests/unit/test_reconciliation.py::TestAStrangerIsAlertedOnce (3). Mutations M37, M38. | L9: None - fixed in the same session
A10: SIT-006 | B10: 2026-09-24 | C10: E15-S09 | D10: HIGH | E10: execution/reconciliation.py + execution/positions.py | F10: Fixed | G10: A restart restored four positions; one had its stop rejected. The loop exited it correctly - and left it in the book as UnverifiedPosition. A ProtectedPosition whose stop died was likewise exited and still labelled ProtectedPosition. The next cycle ran the exit path again: a CRITICAL 'NAKED POSITION ... Closing at market' line and a stop_attach_failures_total increment every 30 seconds for the rest of the day. | H10: The unit test for this exact path asserted the defect. test_a_restored_position_with_no_stop_is_exited ended with 'assert isinstance(manager.tracked(INFY), UnverifiedPosition)' - the test wrote the stale label down as correct behaviour, so it could not fail. The SIT assertion was about the END state of a restart ('nothing may still be unknown'), which is a question about the book rather than about the call. | I10: open_from_fill records ExitingPosition when attach fails; the reconciler exited through the same path and recorded nothing. The book then claimed a protection the broker had just disproved - the one state E15-S05's three types exist to make impossible. Graded HIGH because it is a silent wrong answer in the book, and because the repeated CRITICAL line degrades the one alert channel naked positions have. | J10: PositionManager.mark_exiting, called after exit_now succeeds (exit_now verifies the exit is live and raises having halted if not). A FAILED exit leaves the label alone: there is no live exit, and calling it EXITING would be the same false claim in the other direction. | K10: tests/sit/...::TestSit19...::test_a_restart_resolves_every_restored_position_in_one_cycle; tests/unit/test_reconciliation.py::TestAnExitedPositionSaysSo (5). Mutation M36. | L10: None - fixed in the same session
A11: SIT-007 | B11: 2026-09-24 | C11: E15-S09 | D11: LOW | E11: tests/sit (test infrastructure, Windows only) | F11: Fixed | G11: The full suite hung - zero CPU, no output - inside SIT, in a test that passes in 2.7 s alone. Three runs hung this way across two days, including the E15-S05 SIT runs against the QA worktree. | H11: Linux CI cannot see it: Linux has a native socketpair syscall. On Windows it needs enough event loops in ONE process for a rare loopback failure to happen, which is why it passed alone and hung in the suite. | I11: Every asyncio.run builds a new event loop; on Windows each loop's self-pipe is socket.socketpair(), which CPython emulates with a real loopback TCP connection and then waits for in accept() with NO timeout. The SIT module walks sessions minute by minute and created thousands of loops per test. The pytest faulthandler dump showed the test blocked in socketpair -> accept, and the process's socket table showed a 127.0.0.1 listener in LISTEN with no peer ever connected. THE EARLIER DIAGNOSIS WAS WRONG: on 24 Sep the E15-S05 QA stall was attributed to orphaned pytest processes, 'confirmed' by the next run passing after they were killed. The pass was coincidence - a probabilistic hang that did not recur on that run. | J11: One event loop per SIT module via asyncio.Runner (closer to production, which runs one long-lived loop): SIT went from 49-78 s to 17 s with no hang. faulthandler_timeout = 300 in pytest config, so any future hang dumps every thread's stack instead of waiting in silence. Production is unaffected. | K11: No test can prove a probabilistic hang absent. The structural change removes the thousands of loop creations that made it likely, and faulthandler_timeout turns any recurrence into a named stack rather than a silent stall. | L11: None - fixed in the same session
A12: SIT-008 | B12: 2026-10-27 | C12: E15-S12 (harness) | D12: LOW | E12: tests/sit/test_e14_trading_session.py | F12: Fixed | G12: Every gateway submission in the SIT suite paired a stored RiskDecision with a FRESHLY MINTED Recommendation - a different correlation id each time. 22 SIT scenarios failed with DecisionMismatchError the moment AUDIT-006 made the decision carry its identity. | H12: Nothing could see it: a decision carried no identity, so any pairing 'worked'. The harness was correct about everything it asserted and still exercised the exact wiring defect AUDIT-006 closes. | I12: Session.run kept the decision and threw away the recommendation it was evaluated with; submission sites re-minted one from the minute's timestamp. | J12: Session.recommendations holds the recommendation each minute was evaluated with; all 11 submission sites use it. | K12: The gateway's DecisionMismatchError itself, on every SIT submission (181 SIT passing). | L12: None - fixed in the session.

Sheet Sprint Plan
A1: SUGGESTED SPRINT SEQUENCE
A2: Two-week sprints, solo. Each ends with something demonstrable.
A4: Sprint | B4: Focus | C4: Key Deliverable | D4: Status | E4: Start Date | F4: End Date | G4: Notes
A5: 1 | B5: E01-S01..S04 + S07/S08 (re-scoped) + B1/B3/B4/B6 | C5: Schema, repositories, Redis, streams live; merge gate green; blockers actioned | D5: Active | E5: 46240 | F5: 46244 | G5: RE-SCOPED after the E01 deep dive (EPIC01_TECHNICAL_SPEC.md §16), then updated 7 Aug when two missing stories were added. CAPACITY FINDING — READ FIRST. E01 as originally scoped was 8.5 days against a nominal 5-day sprint that ALSO carries blocker resolution. Deferring E01-S05 and E01-S06 brought it to 7 days; adding E01-S08 (lint debt, 0.5 d) makes it 7.5 d of REMAINING work. E01-S07 (1 d) is already CLOSED. There is no second developer to parallelise across. Do not close the gap by compressing estimates — that produces the same overrun with less visibility. OPTION A (RECOMMENDED, reflected here): let Sprint 1 run to ~7.5 working days. Dates are indicative, so Sprint 1 is 'done when E01-S01..S04 and S08 are done', not a fixed calendar box. OPTION B: hard 5-day box — Sprint 1 keeps E01-S01 + E01-S03 + E01-S08 + blockers (4 d), and E01-S02 + E01-S04 join E01-S05 in Sprint 2. ORDER (Option A): Days 1-2 — E01-S01 (2 d). Send the Zerodha questions (B1 + B4) on day 1, FIRST thing; the answers take days. Day 2 — B3 holiday circular alongside S01; independent desk work. Days 3-4 — E01-S03 Redis (1.5 d). Independent of S01. Days 5-6 — E01-S02 repositories (2 d). Needs S01. Days 6-7 — E01-S04 streams (1.5 d). Needs S03. Day 7 — E01-S08 lint debt (0.5 d), BEFORE E01-S01 merges; sprint review. B6 static IP runs in the background all sprint — procurement lead time. ALREADY DONE: E01-S07 (datastore scaffolding + Alembic bootstrap) closed 7 Aug. It was not in the original backlog even though E01-S01 task 1 assumed all of it existed. Four blockers were found by executing it — see that story's Notes and Code/SETUP.md. DEFERRED OUT: E01-S05 audit hash chain (1 d, only safety-critical story in the epic, moved to Sprint 2) and E01-S06 retention (P2/Phase 6). BLOCKERS: B1, B3, B4, B6 active. B2 decided — wait for release, no work. B5 not Sprint 1, needs E02. GATE ON DAY 1: settle the TimescaleDB pin. Evidence is now empirical — 2.17.2 exposes add_compression_policy ONLY; 2.29.1 exposes BOTH, so the upgrade is backward compatible. Recommend upgrading before the first migration. See Code/SETUP.md Step 2.
A6: 2 | B6: E01-S05 (deferred in) + E03 + E04 | C6: Audit chain verified; historical data flowing, hazard lists daily | D6: New | G6: E01-S05 (audit log writer with hash chaining) carried in from Sprint 1. Safety-critical: budget the full 1 day, schedule it EARLY in the sprint, and do not merge it at the end of a session. Its DoD adds a property-based test over generated event sequences, a tamper test, an outage test, and a second read on a different day. Depends on E01-S01 only, which lands in Sprint 1.
A7: 3 | B7: E02-S01..S03, E05-S01..S05 | C7: Live ticks arriving and cleaned | D7: New
A8: 4 | B8: E05-S06..S08, E06-S01..S03 | C8: Bars building, indicators warm | D8: New
A9: 5 | B9: E06-S04..S07, E07 | C9: Ranked watchlist every morning | D9: New
A10: 6 | B10: E09, E19-S01..S02 | C10: Macro context + Telegram working | D10: New
A11: 7 | B11: E08, E10-S01..S04 | C11: News scored, AI layer live | D11: New
A12: 8 | B12: E11 | C12: Pre-market plan by 09:15 — the inflection point | D12: New
A13: 9 | B13: E10-S05, E13, E17-S01..S03 | C13: Live signals with rationale, dashboard | D13: New
A14: 10 | B14: E14 | C14: Risk engine complete, property-tested | D14: New
A15: 11 | B15: E15-S01..S07 | C15: Order execution on paper | D15: New
A16: 12 | B16: E15-S08..S11, E16 | C16: Position management, autonomy, approval | D16: New
A17: 13 | B17: E12-S01..S08 | C17: Strategy registry + validation gauntlet | D17: New
A18: 14 | B18: E12-S09..S10, E20 | C18: Shadow mode, observability | D18: New
... A23: 19+ | B23: PRE_LIVE_CHECKLIST | C23: Approval mode, small live size | D23: New

Sheet Reference
A1: REFERENCE & LEGEND
A2: Definitions for every classifier used in the Backlog sheet.
A4: STATUS VALUES (dropdown in Backlog column E)
A5: Status | B5: Meaning
A6: New | B6: Captured, not yet triaged.
A7: Business Review | B7: Under review for business value / scope.
A8: Business Approved | B8: Signed off; cleared to be scheduled.
A9: Active | B9: Scheduled into the current sprint; not yet started.
A10: Development In-Progress | B10: Being built.
A11: Development Completed | B11: Code complete, awaiting QA.
A12: QA In-Progress | B12: Under test.
A13: QA-Success | B13: Passed test; ready to close.
A14: QA-Fail | B14: Failed test; returns to development.
A15: Closed | B15: Done and accepted. Definition of Done met.
A16: Removed | B16: Cancelled; will not be built.
... A19: On Hold | B19: Paused by choice rather than by a blocker.
A22: PRIORITY
A23: Value | B23: Meaning
A24: P0 | B24: Blocker — cannot ship without it
A25: P1 | B25: MVP scope
A26: P2 | B26: Post-MVP
A27: P3 | B27: Nice-to-have
A30: RISK
A31: Value | B31: Meaning
A32: Safety-critical | B32: 🔴 A defect can lose money or breach regulation. Needs property-based tests, 100% line coverage, and a second read before merge. Never merge at the end of a session.
A33: Correctness-critical | B33: 🟠 A defect produces wrong results but does not directly risk capital.
A34: Low | B34: 🟢 Ordinary care applies.
A37: TYPE
A38: Value | B38: Meaning
A39: FEAT | B39: Feature work
A40: INFRA | B40: Infrastructure / plumbing
A41: SEC | B41: Security
A42: TEST | B42: Testing
A43: OPS | B43: Operations / deployment
A44: DOC | B44: Documentation
A47: DEFINITION OF DONE (every story)
A48: ☐ Code written and passing `make check` (lint + types + tests)
A49: ☐ Tests written that FAIL if the story's claim is false — not tests that assert the code shape
A50: ☐ Safety-critical stories: property-based test covering the invariant
A51: ☐ Docstrings explain why, not what
A52: ☐ No secret, no float in a money path, no naive datetime
A53: ☐ `make doctor` still exits 0
A54: ☐ Relevant design document updated if behaviour diverged from spec
A57: NOTE ON SOURCE DATA
A58: The epic map in BACKLOG.md lists E21 as 7 stories, but the document actually defines 8 (E21-S01 … E21-S08). This workbook uses the actual 8. Totals here are therefore 189 stories / ~242 days, against the 188 / ~234 stated in the source.
